{
  "软件学院": {
    "name": "白切鸡",
    "cuisine": "粤菜",
    "rating": 3.2,
    "popularity": 11
  },
  "华东师范大学-河口海岸大楼(中山北路校区)": {
    "name": "炖罐",
    "cuisine": "闽菜",
    "rating": 2.5,
    "popularity": 6
  },
  "第十一宿舍": {
    "name": "符离集烧鸡",
    "cuisine": "徽菜",
    "rating": 3.9,
    "popularity": 3
  },
  "河西餐厅": {
    "name": "臭豆腐",
    "cuisine": "特色小吃",
    "rating": 3.9,
    "popularity": 9
  },
  "国际教育中心": {
    "name": "豚骨拉面",
    "cuisine": "日式",
    "rating": 3.3,
    "popularity": 8
  },
  "理科大楼": {
    "name": "白切鸡",
    "cuisine": "粤菜",
    "rating": 1.9,
    "popularity": 1
  },
  "文史楼": {
    "name": "串串香",
    "cuisine": "麻辣烫 / 火锅",
    "rating": 4.3,
    "popularity": 3
  },
  "文附楼": {
    "name": "章鱼烧",
    "cuisine": "日式",
    "rating": 4.2,
    "popularity": 5
  },
  "科学会堂": {
    "name": "驴打滚",
    "cuisine": "京菜",
    "rating": 4.0,
    "popularity": 9
  },
  "外语学院": {
    "name": "扬州炒饭",
    "cuisine": "苏菜",
    "rating": 4.1,
    "popularity": 5
  },
  "长风一村居民委员会": {
    "name": "烤羊肉串",
    "cuisine": "美食街特色",
    "rating": 3.0,
    "popularity": 3
  },
  "中國工商銀行": {
    "name": "炒面",
    "cuisine": "其他",
    "rating": 3.4,
    "popularity": 9
  },
  "办公楼": {
    "name": "葡萄酒",
    "cuisine": "饮品",
    "rating": 3.3,
    "popularity": 11
  },
  "第十宿舍": {
    "name": "马来西亚肉骨茶",
    "cuisine": "东南亚菜",
    "rating": 3.7,
    "popularity": 4
  },
  "计算机楼": {
    "name": "炸鸡",
    "cuisine": "快餐",
    "rating": 3.2,
    "popularity": 16
  },
  "对外汉语学院办公楼": {
    "name": "美式煎饼",
    "cuisine": "西式",
    "rating": 4.7,
    "popularity": 5
  },
  "中山北路校区大礼堂": {
    "name": "鱼香肉丝",
    "cuisine": "川菜",
    "rating": 3.0,
    "popularity": 1
  },
  "第六宿舍": {
    "name": "米酒",
    "cuisine": "饮品",
    "rating": 3.3,
    "popularity": 12
  },
  "体育馆": {
    "name": "清蒸鱼",
    "cuisine": "海鲜",
    "rating": 5,
    "popularity": 9
  },
  "上海市绿色化学与化工过程绿色化重点实验室": {
    "name": "韩式炸酱面",
    "cuisine": "韩式",
    "rating": 3.5,
    "popularity": 2
  }
}