{
  "黑龙江大学丽泽园学生公寓28栋": {
    "name": "符离集烧鸡",
    "cuisine": "徽菜",
    "rating": 4.7,
    "popularity": 16
  },
  "黑龙江大学丽泽园学生公寓15号": {
    "name": "烤羊肉串",
    "cuisine": "烧烤",
    "rating": 3.6,
    "popularity": 11
  },
  "黑龙江大学丽泽园学生公寓11号": {
    "name": "炒糕粿",
    "cuisine": "闽菜",
    "rating": 3.7,
    "popularity": 7
  },
  "黑龙江大学丽泽园学生公寓17栋": {
    "name": "土耳其肉卷",
    "cuisine": "中东菜",
    "rating": 3.0,
    "popularity": 11
  },
  "丽泽园学生公寓22栋": {
    "name": "烤猪肉串",
    "cuisine": "烧烤",
    "rating": 3.3,
    "popularity": 12
  },
  "黑龙江大学-1号教学楼": {
    "name": "艾窝窝",
    "cuisine": "京菜",
    "rating": 3.7,
    "popularity": 8
  },
  "黑龙江大学丽泽园学生公寓24号": {
    "name": "无为熏鸭",
    "cuisine": "徽菜",
    "rating": 2.3,
    "popularity": 9
  },
  "黑龙江大学丽泽园学生公寓14号": {
    "name": "蒙山山珍",
    "cuisine": "沂蒙菜",
    "rating": 4.0,
    "popularity": 15
  },
  "体育馆": {
    "name": "马卡龙",
    "cuisine": "甜品",
    "rating": 3.9,
    "popularity": 5
  },
  "汇文楼": {
    "name": "京酱肉丝",
    "cuisine": "京菜",
    "rating": 2.9,
    "popularity": 8
  },
  "丽泽园学生公寓21栋": {
    "name": "俄罗斯红菜汤",
    "cuisine": "西式",
    "rating": 3.6,
    "popularity": 15
  },
  "黑大A区食堂": {
    "name": "素什锦",
    "cuisine": "素食",
    "rating": 3.6,
    "popularity": 8
  },
  "黑龙江大学丽泽园学生公寓19栋": {
    "name": "热狗",
    "cuisine": "快餐",
    "rating": 4.4,
    "popularity": 4
  },
  "黑龙江大学老图书馆": {
    "name": "烤海鲜串",
    "cuisine": "烧烤",
    "rating": 3.2,
    "popularity": 13
  },
  "黑大实验楼": {
    "name": "蒜蓉蒸海蛎子",
    "cuisine": "海鲜",
    "rating": 4.0,
    "popularity": 4
  },
  "黑龙江大学丽泽园食堂": {
    "name": "韩式辣白菜炒五花肉",
    "cuisine": "韩式",
    "rating": 5,
    "popularity": 10
  },
  "黑龙江大学留学生公寓": {
    "name": "爆肚",
    "cuisine": "京菜",
    "rating": 4.0,
    "popularity": 11
  },
  "丽泽园学生公寓20栋": {
    "name": "关东煮",
    "cuisine": "快餐",
    "rating": 3.5,
    "popularity": 9
  },
  "黑龙江大学教职工活动中心": {
    "name": "酸豆角炒肉末",
    "cuisine": "湘菜",
    "rating": 3.1,
    "popularity": 1
  },
  "黑龙江大学丽泽园学生公寓10号": {
    "name": "叫化童子鸡",
    "cuisine": "浙菜",
    "rating": 2.9,
    "popularity": 7
  }
}