{
  "学苑公寓7号楼": {
    "name": "宫保鸡丁",
    "cuisine": "川菜",
    "rating": 4.6,
    "popularity": 2
  },
  "世纪钟": {
    "name": "黄山双石",
    "cuisine": "徽菜",
    "rating": 2.4,
    "popularity": 7
  },
  "二号教学楼": {
    "name": "蒜蓉蒸海螺",
    "cuisine": "海鲜",
    "rating": 1.9,
    "popularity": 11
  },
  "学苑公寓6号楼": {
    "name": "毛峰熏鲥鱼",
    "cuisine": "徽菜",
    "rating": 3.2,
    "popularity": 8
  },
  "20号宿舍楼": {
    "name": "韩式炸酱面",
    "cuisine": "韩式",
    "rating": 3.0,
    "popularity": 1
  },
  "嘉园C座": {
    "name": "灌肠",
    "cuisine": "京菜",
    "rating": 5,
    "popularity": 12
  },
  "嘉园B座": {
    "name": "蒜蓉蒸蛏子",
    "cuisine": "海鲜",
    "rating": 2.8,
    "popularity": 12
  },
  "学生一食堂": {
    "name": "珍珠奶茶",
    "cuisine": "饮品",
    "rating": 4.4,
    "popularity": 3
  },
  "机械实验馆": {
    "name": "烤蔬菜串",
    "cuisine": "烧烤",
    "rating": 3.5,
    "popularity": 6
  },
  "东阶梯教室": {
    "name": "芒果糯米饭",
    "cuisine": "甜品",
    "rating": 4.3,
    "popularity": 8
  },
  "7号公寓": {
    "name": "烤鸡翅",
    "cuisine": "美食街特色",
    "rating": 4.2,
    "popularity": 9
  },
  "第七教学楼": {
    "name": "炒面",
    "cuisine": "其他",
    "rating": 5,
    "popularity": 15
  },
  "学苑公寓5号楼": {
    "name": "龙井虾仁",
    "cuisine": "浙菜",
    "rating": 3.3,
    "popularity": 8
  },
  "16号学生公寓": {
    "name": "豚骨拉面",
    "cuisine": "日式",
    "rating": 3.4,
    "popularity": 8
  },
  "18号学生公寓": {
    "name": "印尼炒饭",
    "cuisine": "东南亚菜",
    "rating": 4.3,
    "popularity": 15
  },
  "天佑会堂": {
    "name": "西班牙海鲜饭",
    "cuisine": "西式",
    "rating": 3.9,
    "popularity": 4
  },
  "第八教学楼": {
    "name": "辛拉面",
    "cuisine": "韩式",
    "rating": 4.4,
    "popularity": 9
  },
  "建筑与艺术楼": {
    "name": "珍珠奶茶",
    "cuisine": "饮品",
    "rating": 2.3,
    "popularity": 9
  },
  "19号学生公寓": {
    "name": "关东煮",
    "cuisine": "快餐",
    "rating": 3.7,
    "popularity": 6
  },
  "留园公寓": {
    "name": "豆汁粥",
    "cuisine": "京菜",
    "rating": 3.1,
    "popularity": 3
  }
}