{
  "桂花园": {
    "name": "糖醋鱼块",
    "cuisine": "湘菜",
    "rating": 4.1,
    "popularity": 8
  },
  "第一实验楼": {
    "name": "泰式冬阴功汤",
    "cuisine": "东南亚菜",
    "rating": 3.0,
    "popularity": 3
  },
  "第二餐厅": {
    "name": "臭鳜鱼",
    "cuisine": "徽菜",
    "rating": 3.1,
    "popularity": 16
  },
  "运动馆": {
    "name": "肉串",
    "cuisine": "快餐",
    "rating": 5,
    "popularity": 9
  },
  "海棠园": {
    "name": "剁椒土豆丝",
    "cuisine": "湘菜",
    "rating": 3.6,
    "popularity": 8
  },
  "繁塔楼C区": {
    "name": "拉面",
    "cuisine": "日式",
    "rating": 2.8,
    "popularity": 10
  },
  "第一餐厅": {
    "name": "干炒牛河",
    "cuisine": "粤菜",
    "rating": 3.8,
    "popularity": 17
  },
  "创新大厦": {
    "name": "凉面",
    "cuisine": "特色小吃",
    "rating": 2.8,
    "popularity": 3
  },
  "繁塔楼B区": {
    "name": "烤鸡爪",
    "cuisine": "美食街特色",
    "rating": 3.8,
    "popularity": 15
  },
  "北门": {
    "name": "烤蔬菜串",
    "cuisine": "烧烤",
    "rating": 2.8,
    "popularity": 10
  },
  "牡丹园": {
    "name": "龙井虾仁",
    "cuisine": "浙菜",
    "rating": 4.3,
    "popularity": 2
  },
  "玉兰园": {
    "name": "素包子",
    "cuisine": "素食",
    "rating": 3.9,
    "popularity": 17
  },
  "图书馆": {
    "name": "烤海鲜串",
    "cuisine": "烧烤",
    "rating": 3.5,
    "popularity": 16
  },
  "繁塔楼A区": {
    "name": "腊味合蒸",
    "cuisine": "湘菜",
    "rating": 3.1,
    "popularity": 2
  },
  "青梅园": {
    "name": "米酒",
    "cuisine": "饮品",
    "rating": 4.7,
    "popularity": 12
  },
  "繁塔楼E区": {
    "name": "杏仁豆腐",
    "cuisine": "甜品",
    "rating": 1.2,
    "popularity": 6
  },
  "英林讲堂": {
    "name": "烤牛肉串",
    "cuisine": "烧烤",
    "rating": 4.3,
    "popularity": 6
  },
  "兰亭园": {
    "name": "夫妻肺片",
    "cuisine": "川菜",
    "rating": 4.3,
    "popularity": 1
  },
  "南门": {
    "name": "烤鱿鱼",
    "cuisine": "美食街特色",
    "rating": 3.9,
    "popularity": 12
  },
  "繁塔楼D区": {
    "name": "菠萝油",
    "cuisine": "粤菜",
    "rating": 3.1,
    "popularity": 6
  }
}