{
    "体育馆": "文体活动类建筑",
    "教学12": "教育学术类建筑",
    "教学17": "教育学术类建筑",
    "教学13": "教育学术类建筑",
    "教学15": "教育学术类建筑",
    "教学16": "教育学术类建筑",
    "教学2": "教育学术类建筑",
    "教学1": "教育学术类建筑",
    "教学3": "教育学术类建筑",
    "教学4": "教育学术类建筑",
    "教学5": "教育学术类建筑",
    "教学6": "教育学术类建筑",
    "教学7": "教育学术类建筑",
    "教学8": "教育学术类建筑",
    "教学9": "教育学术类建筑",
    "教学11 江苏师范大学医院": "医疗服务类建筑",
    "教学14": "教育学术类建筑",
    "教学18": "教育学术类建筑",
    "教学19": "教育学术类建筑",
    "教学20": "教育学术类建筑",
    "教学21": "教育学术类建筑",
    "分析测试中心": "科研创新类建筑",
    "教学23A": "教育学术类建筑",
    "教学23B": "教育学术类建筑",
    "教学23C": "教育学术类建筑",
    "教学24": "教育学术类建筑",
    "马可音乐厅": "文体活动类建筑",
    "泉山校区三食堂": "餐饮服务类建筑",
    "泉山校区二食堂": "餐饮服务类建筑",
    "学宿1": "生活类建筑",
    "学宿2": "生活类建筑",
    "学宿3": "生活类建筑",
    "学宿4": "生活类建筑",
    "学宿5": "生活类建筑",
    "学宿6": "生活类建筑",
    "学宿7": "生活类建筑",
    "学宿8": "生活类建筑",
    "学宿9": "生活类建筑",
    "学宿10": "生活类建筑",
    "学宿11": "生活类建筑",
    "学宿12": "生活类建筑",
    "学宿13": "生活类建筑",
    "泉山校区一食堂": "餐饮服务类建筑",
    "教育超市": "商业类建筑",
    "泉南浴室": "生活类建筑",
    "大学生餐厅": "餐饮服务类建筑",
    "国际公寓1": "国际交流类建筑",
    "3": "其他",
    "1": "其他",
    "学宿20": "生活类建筑",
    "学宿21": "生活类建筑",
    "学宿22": "生活类建筑",
    "三组团": "生活类建筑",
    "学宿26": "生活类建筑",
    "学宿28": "生活类建筑",
    "学宿27": "生活类建筑",
    "五组团": "生活类建筑",
    "学宿17": "生活类建筑",
    "学宿19": "生活类建筑",
    "学宿18": "生活类建筑",
    "二组团": "生活类建筑",
    "学宿23": "生活类建筑",
    "学宿25": "生活类建筑",
    "学宿24": "生活类建筑",
    "四组团": "生活类建筑",
    "学宿15": "生活类建筑",
    "学宿16": "生活类建筑",
    "学宿14": "生活类建筑",
    "学宿29": "生活类建筑",
    "学宿31": "生活类建筑",
    "学宿30": "生活类建筑",
    "泉北浴室": "生活类建筑",
    "13": "其他",
    "11": "其他",
    "12 江苏师范大学科文学院餐厅": "餐饮服务类建筑",
    "14": "其他",
    "教学10 敬文图书馆": "文化博览类建筑",
    "教学22": "教育学术类建筑",
    "学宿0": "生活类建筑"
}