{
  "university": "江苏海洋大学",
  "nodes": [
    {
      "id": "n_0",
      "type": "junction",
      "longitude": 119.21773529052734,
      "latitude": 34.61277770996094
    },
    {
      "id": "n_1",
      "type": "junction",
      "longitude": 119.21817779541016,
      "latitude": 34.61042785644531
    },
    {
      "id": "n_2",
      "type": "junction",
      "longitude": 119.21929931640625,
      "latitude": 34.60450744628906
    },
    {
      "id": "n_3",
      "type": "junction",
      "longitude": 119.2193374633789,
      "latitude": 34.60438537597656
    },
    {
      "id": "n_4",
      "type": "junction",
      "longitude": 119.22042846679688,
      "latitude": 34.600399017333984
    },
    {
      "id": "n_5",
      "type": "junction",
      "longitude": 119.22046661376953,
      "latitude": 34.600311279296875
    },
    {
      "id": "n_6",
      "type": "junction",
      "longitude": 119.2208023071289,
      "latitude": 34.59892272949219
    },
    {
      "id": "n_7",
      "type": "junction",
      "longitude": 119.22138977050781,
      "latitude": 34.596431732177734
    },
    {
      "id": "n_8",
      "type": "junction",
      "longitude": 119.2214126586914,
      "latitude": 34.59635925292969
    },
    {
      "id": "n_9",
      "type": "junction",
      "longitude": 119.22144317626953,
      "latitude": 34.59620666503906
    },
    {
      "id": "n_10",
      "type": "junction",
      "longitude": 119.2225570678711,
      "latitude": 34.591617584228516
    },
    {
      "id": "n_11",
      "type": "junction",
      "longitude": 119.22352600097656,
      "latitude": 34.587860107421875
    },
    {
      "id": "n_12",
      "type": "junction",
      "longitude": 119.22362518310547,
      "latitude": 34.58771514892578
    },
    {
      "id": "n_13",
      "type": "junction",
      "longitude": 119.21037292480469,
      "latitude": 34.61168670654297
    },
    {
      "id": "n_14",
      "type": "junction",
      "longitude": 119.21080017089844,
      "latitude": 34.60948181152344
    },
    {
      "id": "n_15",
      "type": "junction",
      "longitude": 119.21080780029297,
      "latitude": 34.60942840576172
    },
    {
      "id": "n_16",
      "type": "junction",
      "longitude": 119.2109603881836,
      "latitude": 34.608612060546875
    },
    {
      "id": "n_17",
      "type": "junction",
      "longitude": 119.21110534667969,
      "latitude": 34.60783386230469
    },
    {
      "id": "n_18",
      "type": "junction",
      "longitude": 119.2112808227539,
      "latitude": 34.60687255859375
    },
    {
      "id": "n_19",
      "type": "junction",
      "longitude": 119.21146392822266,
      "latitude": 34.605865478515625
    },
    {
      "id": "n_20",
      "type": "junction",
      "longitude": 119.21149444580078,
      "latitude": 34.60565185546875
    },
    {
      "id": "n_21",
      "type": "junction",
      "longitude": 119.21172332763672,
      "latitude": 34.60448455810547
    },
    {
      "id": "n_22",
      "type": "junction",
      "longitude": 119.21179962158203,
      "latitude": 34.60404968261719
    },
    {
      "id": "n_23",
      "type": "junction",
      "longitude": 119.2118911743164,
      "latitude": 34.6035270690918
    },
    {
      "id": "n_24",
      "type": "junction",
      "longitude": 119.21688079833984,
      "latitude": 34.60626983642578
    },
    {
      "id": "n_25",
      "type": "junction",
      "longitude": 119.21587371826172,
      "latitude": 34.60614013671875
    },
    {
      "id": "n_26",
      "type": "junction",
      "longitude": 119.21578216552734,
      "latitude": 34.60610580444336
    },
    {
      "id": "n_27",
      "type": "junction",
      "longitude": 119.21574401855469,
      "latitude": 34.606056213378906
    },
    {
      "id": "n_28",
      "type": "junction",
      "longitude": 119.21575927734375,
      "latitude": 34.60593032836914
    },
    {
      "id": "n_29",
      "type": "junction",
      "longitude": 119.21590423583984,
      "latitude": 34.604949951171875
    },
    {
      "id": "n_30",
      "type": "junction",
      "longitude": 119.21589660644531,
      "latitude": 34.60480880737305
    },
    {
      "id": "n_31",
      "type": "junction",
      "longitude": 119.21587371826172,
      "latitude": 34.60468292236328
    },
    {
      "id": "n_32",
      "type": "junction",
      "longitude": 119.21582794189453,
      "latitude": 34.60455322265625
    },
    {
      "id": "n_33",
      "type": "junction",
      "longitude": 119.21586608886719,
      "latitude": 34.6043815612793
    },
    {
      "id": "n_34",
      "type": "junction",
      "longitude": 119.21237182617188,
      "latitude": 34.60969161987305
    },
    {
      "id": "n_35",
      "type": "junction",
      "longitude": 119.21326446533203,
      "latitude": 34.60980987548828
    },
    {
      "id": "n_36",
      "type": "junction",
      "longitude": 119.21609497070312,
      "latitude": 34.610172271728516
    },
    {
      "id": "n_37",
      "type": "junction",
      "longitude": 119.21797943115234,
      "latitude": 34.610408782958984
    },
    {
      "id": "n_38",
      "type": "junction",
      "longitude": 119.215576171875,
      "latitude": 34.604347229003906
    },
    {
      "id": "n_39",
      "type": "junction",
      "longitude": 119.21550750732422,
      "latitude": 34.60450744628906
    },
    {
      "id": "n_40",
      "type": "junction",
      "longitude": 119.21539306640625,
      "latitude": 34.60463333129883
    },
    {
      "id": "n_41",
      "type": "junction",
      "longitude": 119.21537780761719,
      "latitude": 34.604881286621094
    },
    {
      "id": "n_42",
      "type": "junction",
      "longitude": 119.21517181396484,
      "latitude": 34.60588073730469
    },
    {
      "id": "n_43",
      "type": "junction",
      "longitude": 119.2140121459961,
      "latitude": 34.60573196411133
    },
    {
      "id": "n_44",
      "type": "junction",
      "longitude": 119.21566772460938,
      "latitude": 34.61234664916992
    },
    {
      "id": "n_45",
      "type": "junction",
      "longitude": 119.21611022949219,
      "latitude": 34.61008071899414
    },
    {
      "id": "n_46",
      "type": "junction",
      "longitude": 119.21642303466797,
      "latitude": 34.60850143432617
    },
    {
      "id": "n_47",
      "type": "junction",
      "longitude": 119.21282196044922,
      "latitude": 34.61198806762695
    },
    {
      "id": "n_48",
      "type": "junction",
      "longitude": 119.21328735351562,
      "latitude": 34.60970687866211
    },
    {
      "id": "n_49",
      "type": "junction",
      "longitude": 119.21356964111328,
      "latitude": 34.60814666748047
    },
    {
      "id": "n_50",
      "type": "junction",
      "longitude": 119.21366882324219,
      "latitude": 34.607566833496094
    },
    {
      "id": "n_51",
      "type": "junction",
      "longitude": 119.20960998535156,
      "latitude": 34.6076545715332
    },
    {
      "id": "n_52",
      "type": "junction",
      "longitude": 119.21205139160156,
      "latitude": 34.60795211791992
    },
    {
      "id": "n_53",
      "type": "junction",
      "longitude": 119.21251678466797,
      "latitude": 34.60801315307617
    },
    {
      "id": "n_54",
      "type": "junction",
      "longitude": 119.21269226074219,
      "latitude": 34.6080322265625
    },
    {
      "id": "n_55",
      "type": "junction",
      "longitude": 119.21484375,
      "latitude": 34.60830307006836
    },
    {
      "id": "n_56",
      "type": "junction",
      "longitude": 119.21517944335938,
      "latitude": 34.60834503173828
    },
    {
      "id": "n_57",
      "type": "junction",
      "longitude": 119.20884704589844,
      "latitude": 34.61147689819336
    },
    {
      "id": "n_58",
      "type": "junction",
      "longitude": 119.22368621826172,
      "latitude": 34.58787155151367
    },
    {
      "id": "n_59",
      "type": "junction",
      "longitude": 119.22274780273438,
      "latitude": 34.5913200378418
    },
    {
      "id": "n_60",
      "type": "junction",
      "longitude": 119.22267150878906,
      "latitude": 34.59162521362305
    },
    {
      "id": "n_61",
      "type": "junction",
      "longitude": 119.22154998779297,
      "latitude": 34.596221923828125
    },
    {
      "id": "n_62",
      "type": "junction",
      "longitude": 119.22151947021484,
      "latitude": 34.59637451171875
    },
    {
      "id": "n_63",
      "type": "junction",
      "longitude": 119.22091674804688,
      "latitude": 34.598941802978516
    },
    {
      "id": "n_64",
      "type": "junction",
      "longitude": 119.2205810546875,
      "latitude": 34.600318908691406
    },
    {
      "id": "n_65",
      "type": "junction",
      "longitude": 119.2205581665039,
      "latitude": 34.60038757324219
    },
    {
      "id": "n_66",
      "type": "junction",
      "longitude": 119.22053527832031,
      "latitude": 34.600406646728516
    },
    {
      "id": "n_67",
      "type": "junction",
      "longitude": 119.2194595336914,
      "latitude": 34.604393005371094
    },
    {
      "id": "n_68",
      "type": "junction",
      "longitude": 119.21942901611328,
      "latitude": 34.60451126098633
    },
    {
      "id": "n_69",
      "type": "junction",
      "longitude": 119.21891784667969,
      "latitude": 34.6071891784668
    },
    {
      "id": "n_70",
      "type": "junction",
      "longitude": 119.21829223632812,
      "latitude": 34.610435485839844
    },
    {
      "id": "n_71",
      "type": "junction",
      "longitude": 119.21784210205078,
      "latitude": 34.612789154052734
    },
    {
      "id": "n_72",
      "type": "junction",
      "longitude": 119.21463775634766,
      "latitude": 34.60927963256836
    },
    {
      "id": "n_73",
      "type": "junction",
      "longitude": 119.21357727050781,
      "latitude": 34.609153747558594
    },
    {
      "id": "n_74",
      "type": "junction",
      "longitude": 119.21914672851562,
      "latitude": 34.60722732543945
    },
    {
      "id": "n_75",
      "type": "junction",
      "longitude": 119.219970703125,
      "latitude": 34.61214828491211
    },
    {
      "id": "n_76",
      "type": "junction",
      "longitude": 119.21983337402344,
      "latitude": 34.61294937133789
    },
    {
      "id": "n_77",
      "type": "junction",
      "longitude": 119.21844482421875,
      "latitude": 34.61110305786133
    },
    {
      "id": "n_78",
      "type": "junction",
      "longitude": 119.21923828125,
      "latitude": 34.61121368408203
    },
    {
      "id": "n_79",
      "type": "junction",
      "longitude": 119.21827697753906,
      "latitude": 34.61196517944336
    },
    {
      "id": "n_80",
      "type": "junction",
      "longitude": 119.21892547607422,
      "latitude": 34.612060546875
    },
    {
      "id": "n_81",
      "type": "junction",
      "longitude": 119.2134017944336,
      "latitude": 34.60747528076172
    },
    {
      "id": "n_82",
      "type": "junction",
      "longitude": 119.2134780883789,
      "latitude": 34.607112884521484
    },
    {
      "id": "n_83",
      "type": "junction",
      "longitude": 119.21345520019531,
      "latitude": 34.6070442199707
    },
    {
      "id": "n_84",
      "type": "junction",
      "longitude": 119.21342468261719,
      "latitude": 34.60699462890625
    },
    {
      "id": "n_85",
      "type": "junction",
      "longitude": 119.2127456665039,
      "latitude": 34.606910705566406
    },
    {
      "id": "n_86",
      "type": "junction",
      "longitude": 119.21265411376953,
      "latitude": 34.607364654541016
    },
    {
      "id": "n_87",
      "type": "junction",
      "longitude": 119.21328735351562,
      "latitude": 34.60801696777344
    },
    {
      "id": "n_88",
      "type": "junction",
      "longitude": 119.21253204345703,
      "latitude": 34.60792541503906
    },
    {
      "id": "n_89",
      "type": "junction",
      "longitude": 119.21277618408203,
      "latitude": 34.606773376464844
    },
    {
      "id": "n_90",
      "type": "junction",
      "longitude": 119.21302795410156,
      "latitude": 34.60680389404297
    },
    {
      "id": "n_91",
      "type": "junction",
      "longitude": 119.21308898925781,
      "latitude": 34.60643005371094
    },
    {
      "id": "n_92",
      "type": "junction",
      "longitude": 119.21275329589844,
      "latitude": 34.60636901855469
    },
    {
      "id": "n_93",
      "type": "junction",
      "longitude": 119.212646484375,
      "latitude": 34.606380462646484
    },
    {
      "id": "n_94",
      "type": "junction",
      "longitude": 119.21224975585938,
      "latitude": 34.6067008972168
    },
    {
      "id": "n_95",
      "type": "junction",
      "longitude": 119.21856689453125,
      "latitude": 34.610469818115234
    },
    {
      "id": "n_96",
      "type": "junction",
      "longitude": 119.21812438964844,
      "latitude": 34.61269760131836
    },
    {
      "id": "n_97",
      "type": "junction",
      "longitude": 119.21892547607422,
      "latitude": 34.61280822753906
    },
    {
      "id": "n_98",
      "type": "junction",
      "longitude": 119.21871948242188,
      "latitude": 34.60959243774414
    },
    {
      "id": "n_99",
      "type": "junction",
      "longitude": 119.2194595336914,
      "latitude": 34.605712890625
    },
    {
      "id": "n_100",
      "type": "junction",
      "longitude": 119.22026062011719,
      "latitude": 34.60582733154297
    },
    {
      "id": "n_101",
      "type": "junction",
      "longitude": 119.2204360961914,
      "latitude": 34.60579299926758
    },
    {
      "id": "n_102",
      "type": "junction",
      "longitude": 119.22050476074219,
      "latitude": 34.60578155517578
    },
    {
      "id": "n_103",
      "type": "junction",
      "longitude": 119.22064208984375,
      "latitude": 34.60578155517578
    },
    {
      "id": "n_104",
      "type": "junction",
      "longitude": 119.22115325927734,
      "latitude": 34.60586166381836
    },
    {
      "id": "n_105",
      "type": "junction",
      "longitude": 119.21952819824219,
      "latitude": 34.60969161987305
    },
    {
      "id": "n_106",
      "type": "junction",
      "longitude": 119.22067260742188,
      "latitude": 34.608333587646484
    },
    {
      "id": "n_107",
      "type": "junction",
      "longitude": 119.22058868408203,
      "latitude": 34.60843276977539
    },
    {
      "id": "n_108",
      "type": "junction",
      "longitude": 119.22049713134766,
      "latitude": 34.608463287353516
    },
    {
      "id": "n_109",
      "type": "junction",
      "longitude": 119.22014617919922,
      "latitude": 34.60868835449219
    },
    {
      "id": "n_110",
      "type": "junction",
      "longitude": 119.2199478149414,
      "latitude": 34.60882568359375
    },
    {
      "id": "n_111",
      "type": "junction",
      "longitude": 119.21984100341797,
      "latitude": 34.60892868041992
    },
    {
      "id": "n_112",
      "type": "junction",
      "longitude": 119.21975708007812,
      "latitude": 34.609073638916016
    },
    {
      "id": "n_113",
      "type": "junction",
      "longitude": 119.21971893310547,
      "latitude": 34.60924530029297
    },
    {
      "id": "n_114",
      "type": "junction",
      "longitude": 119.2197265625,
      "latitude": 34.60938262939453
    },
    {
      "id": "n_115",
      "type": "junction",
      "longitude": 119.21977233886719,
      "latitude": 34.6094856262207
    },
    {
      "id": "n_116",
      "type": "junction",
      "longitude": 119.21975708007812,
      "latitude": 34.60961151123047
    },
    {
      "id": "n_117",
      "type": "junction",
      "longitude": 119.21968078613281,
      "latitude": 34.60966491699219
    },
    {
      "id": "n_118",
      "type": "junction",
      "longitude": 119.21871185302734,
      "latitude": 34.60975646972656
    },
    {
      "id": "n_119",
      "type": "junction",
      "longitude": 119.2197494506836,
      "latitude": 34.60987091064453
    },
    {
      "id": "n_120",
      "type": "junction",
      "longitude": 119.21973419189453,
      "latitude": 34.61003112792969
    },
    {
      "id": "n_121",
      "type": "junction",
      "longitude": 119.21907806396484,
      "latitude": 34.61202621459961
    },
    {
      "id": "n_122",
      "type": "junction",
      "longitude": 119.2191162109375,
      "latitude": 34.61053466796875
    },
    {
      "id": "n_123",
      "type": "junction",
      "longitude": 119.21914672851562,
      "latitude": 34.61037826538086
    },
    {
      "id": "n_124",
      "type": "junction",
      "longitude": 119.2201919555664,
      "latitude": 34.610496520996094
    },
    {
      "id": "n_125",
      "type": "junction",
      "longitude": 119.2202377319336,
      "latitude": 34.61051559448242
    },
    {
      "id": "n_126",
      "type": "junction",
      "longitude": 119.22026824951172,
      "latitude": 34.610538482666016
    },
    {
      "id": "n_127",
      "type": "junction",
      "longitude": 119.22027587890625,
      "latitude": 34.61057662963867
    },
    {
      "id": "n_128",
      "type": "junction",
      "longitude": 119.2192611694336,
      "latitude": 34.61055374145508
    },
    {
      "id": "n_129",
      "type": "junction",
      "longitude": 119.21932983398438,
      "latitude": 34.61060333251953
    },
    {
      "id": "n_130",
      "type": "junction",
      "longitude": 119.21935272216797,
      "latitude": 34.61065673828125
    },
    {
      "id": "n_131",
      "type": "junction",
      "longitude": 119.21253967285156,
      "latitude": 34.60880661010742
    },
    {
      "id": "n_132",
      "type": "junction",
      "longitude": 119.2113265991211,
      "latitude": 34.60865783691406
    },
    {
      "id": "n_133",
      "type": "junction",
      "longitude": 119.20996856689453,
      "latitude": 34.609317779541016
    },
    {
      "id": "n_134",
      "type": "junction",
      "longitude": 119.20951843261719,
      "latitude": 34.611576080322266
    },
    {
      "id": "n_135",
      "type": "junction",
      "longitude": 119.21048736572266,
      "latitude": 34.605533599853516
    },
    {
      "id": "n_136",
      "type": "junction",
      "longitude": 119.21046447753906,
      "latitude": 34.605712890625
    },
    {
      "id": "n_137",
      "type": "junction",
      "longitude": 119.2104721069336,
      "latitude": 34.605838775634766
    },
    {
      "id": "n_138",
      "type": "junction",
      "longitude": 119.21052551269531,
      "latitude": 34.60593795776367
    },
    {
      "id": "n_139",
      "type": "junction",
      "longitude": 119.2110366821289,
      "latitude": 34.605613708496094
    },
    {
      "id": "n_140",
      "type": "junction",
      "longitude": 119.2100830078125,
      "latitude": 34.605472564697266
    },
    {
      "id": "n_141",
      "type": "junction",
      "longitude": 119.21051025390625,
      "latitude": 34.606834411621094
    },
    {
      "id": "n_142",
      "type": "junction",
      "longitude": 119.20984649658203,
      "latitude": 34.60675811767578
    },
    {
      "id": "n_143",
      "type": "junction",
      "longitude": 119.20983123779297,
      "latitude": 34.6070556640625
    },
    {
      "id": "n_144",
      "type": "junction",
      "longitude": 119.2104721069336,
      "latitude": 34.607139587402344
    },
    {
      "id": "n_145",
      "type": "junction",
      "longitude": 119.2110595703125,
      "latitude": 34.60719680786133
    },
    {
      "id": "n_146",
      "type": "junction",
      "longitude": 119.20979309082031,
      "latitude": 34.607364654541016
    },
    {
      "id": "n_147",
      "type": "junction",
      "longitude": 119.2104263305664,
      "latitude": 34.607425689697266
    },
    {
      "id": "n_148",
      "type": "junction",
      "longitude": 119.21102905273438,
      "latitude": 34.60749435424805
    },
    {
      "id": "n_149",
      "type": "junction",
      "longitude": 119.21051788330078,
      "latitude": 34.60678482055664
    },
    {
      "id": "n_150",
      "type": "junction",
      "longitude": 119.21044158935547,
      "latitude": 34.607383728027344
    },
    {
      "id": "n_151",
      "type": "junction",
      "longitude": 119.21037292480469,
      "latitude": 34.60765075683594
    },
    {
      "id": "n_152",
      "type": "junction",
      "longitude": 119.21039581298828,
      "latitude": 34.60627746582031
    },
    {
      "id": "n_153",
      "type": "junction",
      "longitude": 119.21041870117188,
      "latitude": 34.60613250732422
    },
    {
      "id": "n_154",
      "type": "junction",
      "longitude": 119.2104721069336,
      "latitude": 34.60602569580078
    },
    {
      "id": "n_155",
      "type": "junction",
      "longitude": 119.21056365966797,
      "latitude": 34.60587692260742
    },
    {
      "id": "n_156",
      "type": "junction",
      "longitude": 119.210693359375,
      "latitude": 34.60576248168945
    },
    {
      "id": "n_157",
      "type": "junction",
      "longitude": 119.21086883544922,
      "latitude": 34.605674743652344
    },
    {
      "id": "n_158",
      "type": "junction",
      "longitude": 119.2123031616211,
      "latitude": 34.60597229003906
    },
    {
      "id": "n_159",
      "type": "junction",
      "longitude": 119.2122573852539,
      "latitude": 34.60454177856445
    },
    {
      "id": "n_160",
      "type": "junction",
      "longitude": 119.21234893798828,
      "latitude": 34.604576110839844
    },
    {
      "id": "n_161",
      "type": "junction",
      "longitude": 119.21240234375,
      "latitude": 34.60464859008789
    },
    {
      "id": "n_162",
      "type": "junction",
      "longitude": 119.21278381347656,
      "latitude": 34.60554885864258
    },
    {
      "id": "n_163",
      "type": "junction",
      "longitude": 119.21284484863281,
      "latitude": 34.60572814941406
    },
    {
      "id": "n_164",
      "type": "junction",
      "longitude": 119.21284484863281,
      "latitude": 34.605857849121094
    },
    {
      "id": "n_165",
      "type": "junction",
      "longitude": 119.21280670166016,
      "latitude": 34.60602951049805
    },
    {
      "id": "n_166",
      "type": "junction",
      "longitude": 119.2122802734375,
      "latitude": 34.606876373291016
    },
    {
      "id": "n_167",
      "type": "junction",
      "longitude": 119.2122802734375,
      "latitude": 34.60679244995117
    },
    {
      "id": "n_168",
      "type": "junction",
      "longitude": 119.21221160888672,
      "latitude": 34.606632232666016
    },
    {
      "id": "n_169",
      "type": "junction",
      "longitude": 119.21220397949219,
      "latitude": 34.60655975341797
    },
    {
      "id": "n_170",
      "type": "junction",
      "longitude": 119.21428680419922,
      "latitude": 34.60435485839844
    },
    {
      "id": "n_171",
      "type": "junction",
      "longitude": 119.2159423828125,
      "latitude": 34.60403060913086
    },
    {
      "id": "n_172",
      "type": "junction",
      "longitude": 119.21563720703125,
      "latitude": 34.60399627685547
    },
    {
      "id": "n_173",
      "type": "junction",
      "longitude": 119.21910858154297,
      "latitude": 34.60448455810547
    },
    {
      "id": "n_174",
      "type": "junction",
      "longitude": 119.21908569335938,
      "latitude": 34.60466766357422
    },
    {
      "id": "n_175",
      "type": "junction",
      "longitude": 119.21902465820312,
      "latitude": 34.60498046875
    },
    {
      "id": "n_176",
      "type": "junction",
      "longitude": 119.2175521850586,
      "latitude": 34.612545013427734
    },
    {
      "id": "n_177",
      "type": "junction",
      "longitude": 119.21752166748047,
      "latitude": 34.612586975097656
    },
    {
      "id": "n_178",
      "type": "junction",
      "longitude": 119.21839141845703,
      "latitude": 34.60694885253906
    },
    {
      "id": "n_179",
      "type": "junction",
      "longitude": 119.2184829711914,
      "latitude": 34.60647964477539
    },
    {
      "id": "n_180",
      "type": "junction",
      "longitude": 119.21788024902344,
      "latitude": 34.60688400268555
    },
    {
      "id": "n_181",
      "type": "junction",
      "longitude": 119.21831512451172,
      "latitude": 34.60737609863281
    },
    {
      "id": "n_182",
      "type": "junction",
      "longitude": 119.21795654296875,
      "latitude": 34.60641098022461
    },
    {
      "id": "n_183",
      "type": "junction",
      "longitude": 119.21783447265625,
      "latitude": 34.60710144042969
    },
    {
      "id": "n_184",
      "type": "junction",
      "longitude": 119.21780395507812,
      "latitude": 34.60723876953125
    },
    {
      "id": "n_185",
      "type": "junction",
      "longitude": 119.21772766113281,
      "latitude": 34.60480880737305
    },
    {
      "id": "n_186",
      "type": "junction",
      "longitude": 119.21741485595703,
      "latitude": 34.60634231567383
    },
    {
      "id": "n_187",
      "type": "junction",
      "longitude": 119.21721649169922,
      "latitude": 34.60631561279297
    },
    {
      "id": "n_188",
      "type": "junction",
      "longitude": 119.217041015625,
      "latitude": 34.60710906982422
    },
    {
      "id": "n_189",
      "type": "junction",
      "longitude": 119.21719360351562,
      "latitude": 34.60712814331055
    },
    {
      "id": "n_190",
      "type": "junction",
      "longitude": 119.21711730957031,
      "latitude": 34.60750198364258
    },
    {
      "id": "n_191",
      "type": "junction",
      "longitude": 119.21713256835938,
      "latitude": 34.60760498046875
    },
    {
      "id": "n_192",
      "type": "junction",
      "longitude": 119.21717834472656,
      "latitude": 34.60769271850586
    },
    {
      "id": "n_193",
      "type": "junction",
      "longitude": 119.21469116210938,
      "latitude": 34.607688903808594
    },
    {
      "id": "n_194",
      "type": "junction",
      "longitude": 119.21490478515625,
      "latitude": 34.606632232666016
    },
    {
      "id": "n_195",
      "type": "junction",
      "longitude": 119.21562194824219,
      "latitude": 34.606719970703125
    },
    {
      "id": "n_196",
      "type": "junction",
      "longitude": 119.21541595458984,
      "latitude": 34.60777282714844
    },
    {
      "id": "n_197",
      "type": "junction",
      "longitude": 119.21575164794922,
      "latitude": 34.60673522949219
    },
    {
      "id": "n_198",
      "type": "junction",
      "longitude": 119.21529388427734,
      "latitude": 34.6066780090332
    },
    {
      "id": "n_199",
      "type": "junction",
      "longitude": 119.21465301513672,
      "latitude": 34.60660171508789
    },
    {
      "id": "n_200",
      "type": "junction",
      "longitude": 119.21451568603516,
      "latitude": 34.60987091064453
    },
    {
      "id": "n_201",
      "type": "junction",
      "longitude": 119.21489715576172,
      "latitude": 34.609920501708984
    },
    {
      "id": "b_0",
      "type": "building",
      "longitude": 119.21399741212096,
      "latitude": 34.608677484629624,
      "name": "测绘楼",
      "building_type": "school"
    },
    {
      "id": "b_1",
      "type": "building",
      "longitude": 119.21565485214579,
      "latitude": 34.608872806024024,
      "name": "电子楼",
      "building_type": "school"
    },
    {
      "id": "b_2",
      "type": "building",
      "longitude": 119.2139254345537,
      "latitude": 34.60941043672108,
      "name": "haigonglou",
      "building_type": "school"
    },
    {
      "id": "b_3",
      "type": "building",
      "longitude": 119.21921439538217,
      "latitude": 34.61004464942993,
      "name": "D5餐厅",
      "building_type": "yes"
    },
    {
      "id": "b_4",
      "type": "building",
      "longitude": 119.21876866459392,
      "latitude": 34.611516221155334,
      "name": "D7-D8",
      "building_type": "school"
    },
    {
      "id": "b_5",
      "type": "building",
      "longitude": 119.21730018831926,
      "latitude": 34.6091417781737,
      "name": "江苏海洋大学体育馆",
      "building_type": "yes"
    },
    {
      "id": "b_6",
      "type": "building",
      "longitude": 119.21428026530054,
      "latitude": 34.60729987090925,
      "name": "海洋学院",
      "building_type": "college"
    },
    {
      "id": "b_7",
      "type": "building",
      "longitude": 119.21433771634577,
      "latitude": 34.60640169328793,
      "name": "土木工程学院",
      "building_type": "college"
    },
    {
      "id": "b_8",
      "type": "building",
      "longitude": 119.21535697969331,
      "latitude": 34.60640088180066,
      "name": "教学主楼",
      "building_type": "college"
    },
    {
      "id": "b_9",
      "type": "building",
      "longitude": 119.21597040170292,
      "latitude": 34.60754747973008,
      "name": "计算机学院",
      "building_type": "college"
    },
    {
      "id": "b_10",
      "type": "building",
      "longitude": 119.21636821731369,
      "latitude": 34.6066107921976,
      "name": "机械工程学院",
      "building_type": "college"
    },
    {
      "id": "b_11",
      "type": "building",
      "longitude": 119.21300586818361,
      "latitude": 34.60769167649928,
      "name": "大学生活动中心",
      "building_type": "yes"
    },
    {
      "id": "b_12",
      "type": "building",
      "longitude": 119.21236490615452,
      "latitude": 34.60775584661195,
      "name": "第二食堂",
      "building_type": "yes"
    },
    {
      "id": "b_13",
      "type": "building",
      "longitude": 119.21312437786045,
      "latitude": 34.607176618645,
      "name": "第三食堂",
      "building_type": "yes"
    },
    {
      "id": "b_14",
      "type": "building",
      "longitude": 119.21297966409405,
      "latitude": 34.6088013579295,
      "name": "学生宿舍",
      "building_type": "dormitory"
    },
    {
      "id": "b_15",
      "type": "building",
      "longitude": 119.21138381958008,
      "latitude": 34.60921859741211,
      "name": "学生宿舍",
      "building_type": "dormitory"
    },
    {
      "id": "b_16",
      "type": "building",
      "longitude": 119.21146073075613,
      "latitude": 34.60842621396694,
      "name": "学生宿舍",
      "building_type": "dormitory"
    },
    {
      "id": "b_17",
      "type": "building",
      "longitude": 119.2101190549965,
      "latitude": 34.6106890786056,
      "name": "学生宿舍",
      "building_type": "dormitory"
    },
    {
      "id": "b_18",
      "type": "building",
      "longitude": 119.20947688841932,
      "latitude": 34.61027080622376,
      "name": "学生宿舍",
      "building_type": "dormitory"
    },
    {
      "id": "b_19",
      "type": "building",
      "longitude": 119.21507763258265,
      "latitude": 34.60804270718607,
      "name": "文予楼",
      "building_type": "university"
    },
    {
      "id": "b_20",
      "type": "building",
      "longitude": 119.21251906746434,
      "latitude": 34.60651921432671,
      "name": "教工餐厅",
      "building_type": "yes"
    },
    {
      "id": "b_21",
      "type": "building",
      "longitude": 119.21286908939605,
      "latitude": 34.6066010986779,
      "name": "南园餐厅",
      "building_type": "yes"
    },
    {
      "id": "b_22",
      "type": "building",
      "longitude": 119.21204479498506,
      "latitude": 34.6071198760237,
      "name": "超市",
      "building_type": "yes"
    },
    {
      "id": "b_23",
      "type": "building",
      "longitude": 119.21191847845361,
      "latitude": 34.60671764806813,
      "name": "卫生所",
      "building_type": "yes"
    },
    {
      "id": "b_24",
      "type": "building",
      "longitude": 119.21354597345594,
      "latitude": 34.606542671920096,
      "name": "水房",
      "building_type": "bungalow"
    },
    {
      "id": "b_25",
      "type": "building",
      "longitude": 119.21486566767364,
      "latitude": 34.60472467114943,
      "name": "行政楼",
      "building_type": "office"
    },
    {
      "id": "b_26",
      "type": "building",
      "longitude": 119.21761141697672,
      "latitude": 34.607494410697676,
      "name": "艺术院",
      "building_type": "school"
    },
    {
      "id": "b_27",
      "type": "building",
      "longitude": 119.2175323811763,
      "latitude": 34.60673261611855,
      "name": "食品工程学院",
      "building_type": "school"
    },
    {
      "id": "b_28",
      "type": "building",
      "longitude": 119.21833479791927,
      "latitude": 34.605811567395556,
      "name": "定海楼（理学院）",
      "building_type": "yes"
    },
    {
      "id": "b_29",
      "type": "building",
      "longitude": 119.21800782659956,
      "latitude": 34.60542517370842,
      "name": "工程训练中心",
      "building_type": "yes"
    },
    {
      "id": "b_30",
      "type": "building",
      "longitude": 119.2115243596616,
      "latitude": 34.608054040549455,
      "name": "学生宿舍",
      "building_type": "dormitory"
    },
    {
      "id": "b_31",
      "type": "building",
      "longitude": 119.21210788901335,
      "latitude": 34.60930915284001,
      "name": "学生宿舍",
      "building_type": "dormitory"
    },
    {
      "id": "b_32",
      "type": "building",
      "longitude": 119.21217635643755,
      "latitude": 34.60892186958252,
      "name": "学生宿舍",
      "building_type": "dormitory"
    },
    {
      "id": "b_33",
      "type": "building",
      "longitude": 119.21136794356028,
      "latitude": 34.608816980613135,
      "name": "学生宿舍",
      "building_type": "dormitory"
    },
    {
      "id": "b_34",
      "type": "building",
      "longitude": 119.21306436472926,
      "latitude": 34.60829106473374,
      "name": "b1宿舍",
      "building_type": "apartments"
    },
    {
      "id": "b_35",
      "type": "building",
      "longitude": 119.212987612118,
      "latitude": 34.60863973464244,
      "name": "b2宿舍",
      "building_type": "apartments"
    },
    {
      "id": "b_36",
      "type": "building",
      "longitude": 119.21294753638664,
      "latitude": 34.60898102012473,
      "name": "b3宿舍",
      "building_type": "apartments"
    },
    {
      "id": "b_37",
      "type": "building",
      "longitude": 119.21288318944171,
      "latitude": 34.60932804123173,
      "name": "b4宿舍",
      "building_type": "apartments"
    }
  ],
  "edges": [
    {
      "source": "n_0",
      "target": "n_1",
      "weight": 526.0540945800831,
      "distance": 239.11549753640134,
      "road_type": "secondary",
      "weight_factor": 2.2
    },
    {
      "source": "n_1",
      "target": "n_2",
      "weight": 1325.6540962576596,
      "distance": 602.5700437534816,
      "road_type": "secondary",
      "weight_factor": 2.2
    },
    {
      "source": "n_1",
      "target": "n_37",
      "weight": 27.899079957965952,
      "distance": 19.927914255689966,
      "road_type": "service",
      "weight_factor": 1.4
    },
    {
      "source": "n_2",
      "target": "n_3",
      "weight": 28.136230584204455,
      "distance": 12.789195720092934,
      "road_type": "secondary",
      "weight_factor": 2.2
    },
    {
      "source": "n_3",
      "target": "n_4",
      "weight": 909.250809385066,
      "distance": 413.29582244775725,
      "road_type": "secondary",
      "weight_factor": 2.2
    },
    {
      "source": "n_4",
      "target": "n_5",
      "weight": 21.047866553318634,
      "distance": 9.567212069690287,
      "road_type": "secondary",
      "weight_factor": 2.2
    },
    {
      "source": "n_5",
      "target": "n_6",
      "weight": 314.2814226687707,
      "distance": 142.8551921221685,
      "road_type": "secondary",
      "weight_factor": 2.2
    },
    {
      "source": "n_6",
      "target": "n_7",
      "weight": 563.0530638944801,
      "distance": 255.93321086112738,
      "road_type": "secondary",
      "weight_factor": 2.2
    },
    {
      "source": "n_7",
      "target": "n_8",
      "weight": 16.721607002020573,
      "distance": 7.6007304554638955,
      "road_type": "secondary",
      "weight_factor": 2.2
    },
    {
      "source": "n_8",
      "target": "n_9",
      "weight": 34.234139800732805,
      "distance": 15.56097263669673,
      "road_type": "secondary",
      "weight_factor": 2.2
    },
    {
      "source": "n_9",
      "target": "n_10",
      "weight": 1038.912985668595,
      "distance": 472.2331753039067,
      "road_type": "secondary",
      "weight_factor": 2.2
    },
    {
      "source": "n_10",
      "target": "n_11",
      "weight": 853.6868421507224,
      "distance": 388.0394737048738,
      "road_type": "secondary",
      "weight_factor": 2.2
    },
    {
      "source": "n_11",
      "target": "n_12",
      "weight": 38.64120750898276,
      "distance": 17.5641852313558,
      "road_type": "secondary",
      "weight_factor": 2.2
    },
    {
      "source": "n_12",
      "target": "n_58",
      "weight": 36.93580504323109,
      "distance": 16.789002292377766,
      "road_type": "secondary",
      "weight_factor": 2.2
    },
    {
      "source": "n_13",
      "target": "n_14",
      "weight": 314.4270740996321,
      "distance": 224.59076721402295,
      "road_type": "service",
      "weight_factor": 1.4
    },
    {
      "source": "n_13",
      "target": "n_47",
      "weight": 345.45107350541946,
      "distance": 246.75076678958536,
      "road_type": "service",
      "weight_factor": 1.4
    },
    {
      "source": "n_13",
      "target": "n_134",
      "weight": 120.62729028055631,
      "distance": 86.16235020039737,
      "road_type": "service",
      "weight_factor": 1.4
    },
    {
      "source": "n_13",
      "target": "b_17",
      "weight": 154.4134258113214,
      "distance": 102.94228387421427,
      "road_type": "footway",
      "weight_factor": 1.5
    },
    {
      "source": "n_14",
      "target": "n_15",
      "weight": 7.55271525315221,
      "distance": 5.394796609394437,
      "road_type": "service",
      "weight_factor": 1.4
    },
    {
      "source": "n_14",
      "target": "n_34",
      "weight": 221.98366810411608,
      "distance": 158.5597629315115,
      "road_type": "service",
      "weight_factor": 1.4
    },
    {
      "source": "n_15",
      "target": "n_16",
      "weight": 116.2676672751631,
      "distance": 83.04833376797365,
      "road_type": "service",
      "weight_factor": 1.4
    },
    {
      "source": "n_15",
      "target": "n_133",
      "weight": 118.5090579327008,
      "distance": 84.6493270947863,
      "road_type": "service",
      "weight_factor": 1.4
    },
    {
      "source": "n_16",
      "target": "n_17",
      "weight": 110.8217812831762,
      "distance": 79.15841520226871,
      "road_type": "service",
      "weight_factor": 1.4
    },
    {
      "source": "n_16",
      "target": "n_132",
      "weight": 51.668521946493385,
      "distance": 36.90608710463813,
      "road_type": "service",
      "weight_factor": 1.4
    },
    {
      "source": "n_17",
      "target": "n_18",
      "weight": 136.80634076969707,
      "distance": 97.71881483549792,
      "road_type": "service",
      "weight_factor": 1.4
    },
    {
      "source": "n_17",
      "target": "n_51",
      "weight": 210.8499783610803,
      "distance": 150.60712740077167,
      "road_type": "service",
      "weight_factor": 1.4
    },
    {
      "source": "n_17",
      "target": "n_52",
      "weight": 133.47701502844126,
      "distance": 95.34072502031519,
      "road_type": "service",
      "weight_factor": 1.4
    },
    {
      "source": "n_17",
      "target": "b_30",
      "weight": 71.00093390732206,
      "distance": 47.33395593821471,
      "road_type": "footway",
      "weight_factor": 1.5
    },
    {
      "source": "n_18",
      "target": "n_19",
      "weight": 143.30269631193718,
      "distance": 102.35906879424086,
      "road_type": "service",
      "weight_factor": 1.4
    },
    {
      "source": "n_18",
      "target": "n_149",
      "weight": 107.51549477583873,
      "distance": 76.79678198274196,
      "road_type": "service",
      "weight_factor": 1.4
    },
    {
      "source": "n_19",
      "target": "n_20",
      "weight": 30.21086101260884,
      "distance": 21.579186437577746,
      "road_type": "service",
      "weight_factor": 1.4
    },
    {
      "source": "n_19",
      "target": "n_158",
      "weight": 118.44044669116671,
      "distance": 84.6003190651191,
      "road_type": "service",
      "weight_factor": 1.4
    },
    {
      "source": "n_20",
      "target": "n_21",
      "weight": 166.5335178612744,
      "distance": 118.95251275805313,
      "road_type": "service",
      "weight_factor": 1.4
    },
    {
      "source": "n_20",
      "target": "n_139",
      "weight": 64.3090530788773,
      "distance": 45.93503791348379,
      "road_type": "service",
      "weight_factor": 1.4
    },
    {
      "source": "n_21",
      "target": "n_22",
      "weight": 61.81241093360108,
      "distance": 44.15172209542934,
      "road_type": "service",
      "weight_factor": 1.4
    },
    {
      "source": "n_21",
      "target": "n_159",
      "weight": 75.19599524101338,
      "distance": 53.71142517215241,
      "road_type": "service",
      "weight_factor": 1.4
    },
    {
      "source": "n_22",
      "target": "n_23",
      "weight": 74.28010017372102,
      "distance": 53.057214409800736,
      "road_type": "service",
      "weight_factor": 1.4
    },
    {
      "source": "n_22",
      "target": "n_170",
      "weight": 350.81691624342136,
      "distance": 250.58351160244385,
      "road_type": "service",
      "weight_factor": 1.4
    },
    {
      "source": "n_24",
      "target": "n_25",
      "weight": 142.15566480482184,
      "distance": 101.53976057487276,
      "road_type": "service",
      "weight_factor": 1.4
    },
    {
      "source": "n_24",
      "target": "n_46",
      "weight": 318.92899626562655,
      "distance": 227.80642590401897,
      "road_type": "service",
      "weight_factor": 1.4
    },
    {
      "source": "n_24",
      "target": "n_187",
      "weight": 47.43201390936939,
      "distance": 33.88000993526385,
      "road_type": "service",
      "weight_factor": 1.4
    },
    {
      "source": "n_24",
      "target": "b_10",
      "weight": 92.34326343076594,
      "distance": 61.56217562051062,
      "road_type": "footway",
      "weight_factor": 1.5
    },
    {
      "source": "n_25",
      "target": "n_26",
      "weight": 13.688970844396067,
      "distance": 9.777836317425763,
      "road_type": "service",
      "weight_factor": 1.4
    },
    {
      "source": "n_25",
      "target": "n_197",
      "weight": 85.0477323375004,
      "distance": 60.74838024107172,
      "road_type": "service",
      "weight_factor": 1.4
    },
    {
      "source": "n_26",
      "target": "n_27",
      "weight": 8.759196187438743,
      "distance": 6.256568705313388,
      "road_type": "service",
      "weight_factor": 1.4
    },
    {
      "source": "n_27",
      "target": "n_28",
      "weight": 17.752897792078038,
      "distance": 12.680641280055742,
      "road_type": "service",
      "weight_factor": 1.4
    },
    {
      "source": "n_28",
      "target": "n_29",
      "weight": 138.7450443236082,
      "distance": 99.10360308829158,
      "road_type": "service",
      "weight_factor": 1.4
    },
    {
      "source": "n_28",
      "target": "n_42",
      "weight": 82.5373909600917,
      "distance": 58.95527925720836,
      "road_type": "service",
      "weight_factor": 1.4
    },
    {
      "source": "n_29",
      "target": "n_30",
      "weight": 19.78897875908544,
      "distance": 14.13498482791817,
      "road_type": "service",
      "weight_factor": 1.4
    },
    {
      "source": "n_30",
      "target": "n_31",
      "weight": 17.912837038992148,
      "distance": 12.794883599280107,
      "road_type": "service",
      "weight_factor": 1.4
    },
    {
      "source": "n_31",
      "target": "n_32",
      "weight": 19.255721228216494,
      "distance": 13.75408659158321,
      "road_type": "service",
      "weight_factor": 1.4
    },
    {
      "source": "n_32",
      "target": "n_33",
      "weight": 24.618839722080313,
      "distance": 17.584885515771653,
      "road_type": "service",
      "weight_factor": 1.4
    },
    {
      "source": "n_32",
      "target": "n_185",
      "weight": 268.35691148621123,
      "distance": 191.6835082044366,
      "road_type": "service",
      "weight_factor": 1.4
    },
    {
      "source": "n_33",
      "target": "n_171",
      "weight": 50.2808935983757,
      "distance": 35.91492399883978,
      "road_type": "service",
      "weight_factor": 1.4
    },
    {
      "source": "n_34",
      "target": "n_35",
      "weight": 126.06135645496899,
      "distance": 90.04382603926358,
      "road_type": "service",
      "weight_factor": 1.4
    },
    {
      "source": "n_34",
      "target": "n_131",
      "weight": 126.10999145754162,
      "distance": 90.07856532681544,
      "road_type": "service",
      "weight_factor": 1.4
    },
    {
      "source": "n_34",
      "target": "b_31",
      "weight": 69.70463928357762,
      "distance": 46.469759522385075,
      "road_type": "footway",
      "weight_factor": 1.5
    },
    {
      "source": "n_35",
      "target": "n_36",
      "weight": 399.50544068665806,
      "distance": 285.36102906189865,
      "road_type": "service",
      "weight_factor": 1.4
    },
    {
      "source": "n_35",
      "target": "n_47",
      "weight": 311.1759930649909,
      "distance": 222.2685664749935,
      "road_type": "service",
      "weight_factor": 1.4
    },
    {
      "source": "n_35",
      "target": "n_48",
      "weight": 14.771303833248187,
      "distance": 10.550931309462989,
      "road_type": "service",
      "weight_factor": 1.4
    },
    {
      "source": "n_36",
      "target": "n_37",
      "weight": 265.89419594535804,
      "distance": 189.92442567525575,
      "road_type": "service",
      "weight_factor": 1.4
    },
    {
      "source": "n_36",
      "target": "n_44",
      "weight": 310.233697482224,
      "distance": 221.59549820158858,
      "road_type": "service",
      "weight_factor": 1.4
    },
    {
      "source": "n_36",
      "target": "n_45",
      "weight": 12.9941826513939,
      "distance": 9.281559036709929,
      "road_type": "service",
      "weight_factor": 1.4
    },
    {
      "source": "n_37",
      "target": "n_175",
      "weight": 773.9239348200003,
      "distance": 552.8028105857145,
      "road_type": "service",
      "weight_factor": 1.4
    },
    {
      "source": "n_37",
      "target": "n_176",
      "weight": 304.99506367925596,
      "distance": 217.85361691375425,
      "road_type": "service",
      "weight_factor": 1.4
    },
    {
      "source": "n_38",
      "target": "n_39",
      "weight": 24.40356982774995,
      "distance": 17.43112130553568,
      "road_type": "service",
      "weight_factor": 1.4
    },
    {
      "source": "n_38",
      "target": "n_172",
      "weight": 49.870802434998325,
      "distance": 35.62200173928452,
      "road_type": "service",
      "weight_factor": 1.4
    },
    {
      "source": "n_39",
      "target": "n_40",
      "weight": 23.81801175641545,
      "distance": 17.01286554029675,
      "road_type": "service",
      "weight_factor": 1.4
    },
    {
      "source": "n_39",
      "target": "n_170",
      "weight": 172.22840648831126,
      "distance": 123.0202903487938,
      "road_type": "service",
      "weight_factor": 1.4
    },
    {
      "source": "n_40",
      "target": "n_41",
      "weight": 34.77941317326493,
      "distance": 24.842437980903526,
      "road_type": "service",
      "weight_factor": 1.4
    },
    {
      "source": "n_40",
      "target": "b_25",
      "weight": 80.28747603518768,
      "distance": 53.52498402345846,
      "road_type": "footway",
      "weight_factor": 1.5
    },
    {
      "source": "n_41",
      "target": "n_42",
      "weight": 142.86415594312615,
      "distance": 102.04582567366154,
      "road_type": "service",
      "weight_factor": 1.4
    },
    {
      "source": "n_42",
      "target": "n_43",
      "weight": 163.68408570114292,
      "distance": 116.91720407224494,
      "road_type": "service",
      "weight_factor": 1.4
    },
    {
      "source": "n_43",
      "target": "n_50",
      "weight": 261.3397730560718,
      "distance": 186.67126646862272,
      "road_type": "service",
      "weight_factor": 1.4
    },
    {
      "source": "n_43",
      "target": "n_170",
      "weight": 196.59196970168708,
      "distance": 140.4228355012051,
      "road_type": "service",
      "weight_factor": 1.4
    },
    {
      "source": "n_44",
      "target": "n_177",
      "weight": 261.72365221371604,
      "distance": 186.94546586694005,
      "road_type": "service",
      "weight_factor": 1.4
    },
    {
      "source": "n_44",
      "target": "n_47",
      "weight": 401.5573505895242,
      "distance": 286.8266789925173,
      "road_type": "service",
      "weight_factor": 1.4
    },
    {
      "source": "n_45",
      "target": "n_46",
      "weight": 225.39509301079158,
      "distance": 160.99649500770826,
      "road_type": "service",
      "weight_factor": 1.4
    },
    {
      "source": "n_45",
      "target": "n_201",
      "weight": 171.30517242254444,
      "distance": 122.36083744467462,
      "road_type": "service",
      "weight_factor": 1.4
    },
    {
      "source": "n_46",
      "target": "n_56",
      "weight": 175.47429954626546,
      "distance": 125.33878539018959,
      "road_type": "service",
      "weight_factor": 1.4
    },
    {
      "source": "n_46",
      "target": "b_5",
      "weight": 162.90295377406397,
      "distance": 108.60196918270931,
      "road_type": "footway",
      "weight_factor": 1.5
    },
    {
      "source": "n_48",
      "target": "n_49",
      "weight": 221.97595882098733,
      "distance": 158.55425630070525,
      "road_type": "service",
      "weight_factor": 1.4
    },
    {
      "source": "n_48",
      "target": "n_200",
      "weight": 173.49311942548812,
      "distance": 123.92365673249152,
      "road_type": "service",
      "weight_factor": 1.4
    },
    {
      "source": "n_48",
      "target": "b_37",
      "weight": 83.0932845618011,
      "distance": 55.395523041200725,
      "road_type": "footway",
      "weight_factor": 1.5
    },
    {
      "source": "n_49",
      "target": "n_50",
      "weight": 82.35577129114297,
      "distance": 58.825550922244986,
      "road_type": "service",
      "weight_factor": 1.4
    },
    {
      "source": "n_49",
      "target": "n_54",
      "weight": 123.87374043762576,
      "distance": 88.48124316973268,
      "road_type": "service",
      "weight_factor": 1.4
    },
    {
      "source": "n_49",
      "target": "n_55",
      "weight": 179.71415749574575,
      "distance": 128.36725535410412,
      "road_type": "service",
      "weight_factor": 1.4
    },
    {
      "source": "n_50",
      "target": "n_193",
      "weight": 144.14411969587567,
      "distance": 102.96008549705407,
      "road_type": "service",
      "weight_factor": 1.4
    },
    {
      "source": "n_51",
      "target": "n_57",
      "weight": 545.6814556488865,
      "distance": 389.77246832063327,
      "road_type": "service",
      "weight_factor": 1.4
    },
    {
      "source": "n_52",
      "target": "n_53",
      "weight": 65.71296320001476,
      "distance": 46.93783085715339,
      "road_type": "service",
      "weight_factor": 1.4
    },
    {
      "source": "n_52",
      "target": "n_166",
      "weight": 153.97539630823562,
      "distance": 109.982425934454,
      "road_type": "service",
      "weight_factor": 1.4
    },
    {
      "source": "n_53",
      "target": "n_54",
      "weight": 24.71134860498502,
      "distance": 17.650963289275015,
      "road_type": "service",
      "weight_factor": 1.4
    },
    {
      "source": "n_53",
      "target": "n_88",
      "weight": 12.467700608749581,
      "distance": 8.90550043482113,
      "road_type": "service",
      "weight_factor": 1.4
    },
    {
      "source": "n_54",
      "target": "n_131",
      "weight": 110.49831494017755,
      "distance": 78.92736781441255,
      "road_type": "service",
      "weight_factor": 1.4
    },
    {
      "source": "n_55",
      "target": "n_56",
      "weight": 47.3628117842856,
      "distance": 33.83057984591829,
      "road_type": "service",
      "weight_factor": 1.4
    },
    {
      "source": "n_55",
      "target": "n_72",
      "weight": 139.72727344279815,
      "distance": 99.8051953162844,
      "road_type": "service",
      "weight_factor": 1.4
    },
    {
      "source": "n_56",
      "target": "n_201",
      "weight": 224.0783826276102,
      "distance": 160.05598759115017,
      "road_type": "service",
      "weight_factor": 1.4
    },
    {
      "source": "n_56",
      "target": "b_1",
      "weight": 106.54849715062937,
      "distance": 71.03233143375293,
      "road_type": "footway",
      "weight_factor": 1.5
    },
    {
      "source": "n_56",
      "target": "b_19",
      "weight": 47.85107423383066,
      "distance": 31.9007161558871,
      "road_type": "footway",
      "weight_factor": 1.5
    },
    {
      "source": "n_57",
      "target": "n_134",
      "weight": 95.01423855318762,
      "distance": 67.86731325227689,
      "road_type": "service",
      "weight_factor": 1.4
    },
    {
      "source": "n_58",
      "target": "n_59",
      "weight": 786.2555514650978,
      "distance": 357.3888870295899,
      "road_type": "secondary",
      "weight_factor": 2.2
    },
    {
      "source": "n_59",
      "target": "n_60",
      "weight": 69.20495892607768,
      "distance": 31.45679951185349,
      "road_type": "secondary",
      "weight_factor": 2.2
    },
    {
      "source": "n_60",
      "target": "n_61",
      "weight": 1040.940736171271,
      "distance": 473.15488007785035,
      "road_type": "secondary",
      "weight_factor": 2.2
    },
    {
      "source": "n_61",
      "target": "n_62",
      "weight": 34.234139800732805,
      "distance": 15.56097263669673,
      "road_type": "secondary",
      "weight_factor": 2.2
    },
    {
      "source": "n_62",
      "target": "n_63",
      "weight": 580.160415516888,
      "distance": 263.7092797804036,
      "road_type": "secondary",
      "weight_factor": 2.2
    },
    {
      "source": "n_63",
      "target": "n_64",
      "weight": 311.83478401008495,
      "distance": 141.7430836409477,
      "road_type": "secondary",
      "weight_factor": 2.2
    },
    {
      "source": "n_64",
      "target": "n_65",
      "weight": 15.92333416527657,
      "distance": 7.237879166034804,
      "road_type": "secondary",
      "weight_factor": 2.2
    },
    {
      "source": "n_65",
      "target": "n_66",
      "weight": 6.554622378156525,
      "distance": 2.9793738082529653,
      "road_type": "secondary",
      "weight_factor": 2.2
    },
    {
      "source": "n_66",
      "target": "n_67",
      "weight": 908.3704288007691,
      "distance": 412.895649454895,
      "road_type": "secondary",
      "weight_factor": 2.2
    },
    {
      "source": "n_67",
      "target": "n_68",
      "weight": 26.868578571991474,
      "distance": 12.212990259996126,
      "road_type": "secondary",
      "weight_factor": 2.2
    },
    {
      "source": "n_68",
      "target": "n_69",
      "weight": 599.7789202254174,
      "distance": 272.62678192064425,
      "road_type": "secondary",
      "weight_factor": 2.2
    },
    {
      "source": "n_69",
      "target": "n_70",
      "weight": 727.3287797264617,
      "distance": 330.6039907847553,
      "road_type": "secondary",
      "weight_factor": 2.2
    },
    {
      "source": "n_69",
      "target": "n_74",
      "weight": 32.485456628484755,
      "distance": 23.203897591774826,
      "road_type": "service",
      "weight_factor": 1.4
    },
    {
      "source": "n_70",
      "target": "n_71",
      "weight": 527.1915651090768,
      "distance": 239.63252959503492,
      "road_type": "secondary",
      "weight_factor": 2.2
    },
    {
      "source": "n_70",
      "target": "n_95",
      "weight": 38.75139145987004,
      "distance": 27.6795653284786,
      "road_type": "service",
      "weight_factor": 1.4
    },
    {
      "source": "n_72",
      "target": "n_73",
      "weight": 149.51038138864732,
      "distance": 106.79312956331954,
      "road_type": "service",
      "weight_factor": 1.4
    },
    {
      "source": "n_72",
      "target": "n_200",
      "weight": 84.52463617954874,
      "distance": 60.3747401282491,
      "road_type": "service",
      "weight_factor": 1.4
    },
    {
      "source": "n_73",
      "target": "b_0",
      "weight": 95.26421381462606,
      "distance": 63.509475876417376,
      "road_type": "footway",
      "weight_factor": 1.5
    },
    {
      "source": "n_73",
      "target": "b_2",
      "weight": 64.88389170040028,
      "distance": 43.25592780026685,
      "road_type": "footway",
      "weight_factor": 1.5
    },
    {
      "source": "n_74",
      "target": "n_98",
      "weight": 336.47494794235945,
      "distance": 240.33924853025673,
      "road_type": "service",
      "weight_factor": 1.4
    },
    {
      "source": "n_74",
      "target": "n_99",
      "weight": 216.4963134798718,
      "distance": 154.64022391419414,
      "road_type": "service",
      "weight_factor": 1.4
    },
    {
      "source": "n_75",
      "target": "n_76",
      "weight": 113.78811614863852,
      "distance": 81.2772258204561,
      "road_type": "service",
      "weight_factor": 1.4
    },
    {
      "source": "n_75",
      "target": "n_121",
      "weight": 126.13260599936375,
      "distance": 90.09471857097412,
      "road_type": "service",
      "weight_factor": 1.4
    },
    {
      "source": "n_75",
      "target": "n_127",
      "weight": 224.141379707797,
      "distance": 160.1009855055693,
      "road_type": "service",
      "weight_factor": 1.4
    },
    {
      "source": "n_77",
      "target": "n_78",
      "weight": 112.1584572579507,
      "distance": 80.11318375567907,
      "road_type": "service",
      "weight_factor": 1.4
    },
    {
      "source": "n_77",
      "target": "n_95",
      "weight": 90.28575330385078,
      "distance": 64.48982378846485,
      "road_type": "service",
      "weight_factor": 1.4
    },
    {
      "source": "n_77",
      "target": "n_79",
      "weight": 122.9632146200204,
      "distance": 87.83086758572885,
      "road_type": "service",
      "weight_factor": 1.4
    },
    {
      "source": "n_77",
      "target": "b_4",
      "weight": 78.74307056748029,
      "distance": 52.495380378320185,
      "road_type": "footway",
      "weight_factor": 1.5
    },
    {
      "source": "n_78",
      "target": "n_130",
      "weight": 79.6014625166058,
      "distance": 56.858187511861296,
      "road_type": "service",
      "weight_factor": 1.4
    },
    {
      "source": "n_78",
      "target": "n_121",
      "weight": 115.94463437774449,
      "distance": 82.8175959841032,
      "road_type": "service",
      "weight_factor": 1.4
    },
    {
      "source": "n_79",
      "target": "n_80",
      "weight": 91.76626735082785,
      "distance": 65.5473338220199,
      "road_type": "service",
      "weight_factor": 1.4
    },
    {
      "source": "n_79",
      "target": "n_96",
      "weight": 104.74066736440287,
      "distance": 74.81476240314491,
      "road_type": "service",
      "weight_factor": 1.4
    },
    {
      "source": "n_81",
      "target": "n_82",
      "weight": 51.84761614709213,
      "distance": 37.03401153363724,
      "road_type": "service",
      "weight_factor": 1.4
    },
    {
      "source": "n_81",
      "target": "n_86",
      "weight": 105.81486147017323,
      "distance": 75.5820439072666,
      "road_type": "service",
      "weight_factor": 1.4
    },
    {
      "source": "n_81",
      "target": "n_87",
      "weight": 77.5101427585981,
      "distance": 55.36438768471293,
      "road_type": "service",
      "weight_factor": 1.4
    },
    {
      "source": "n_82",
      "target": "n_83",
      "weight": 10.133030832448725,
      "distance": 7.237879166034804,
      "road_type": "service",
      "weight_factor": 1.4
    },
    {
      "source": "n_83",
      "target": "n_84",
      "weight": 8.152035725198076,
      "distance": 5.822882660855769,
      "road_type": "service",
      "weight_factor": 1.4
    },
    {
      "source": "n_84",
      "target": "n_85",
      "weight": 95.78558230597991,
      "distance": 68.41827307569994,
      "road_type": "service",
      "weight_factor": 1.4
    },
    {
      "source": "n_84",
      "target": "b_13",
      "weight": 52.67183562748018,
      "distance": 35.114557084986785,
      "road_type": "footway",
      "weight_factor": 1.5
    },
    {
      "source": "n_84",
      "target": "b_24",
      "weight": 70.1924010146812,
      "distance": 46.79493400978746,
      "road_type": "footway",
      "weight_factor": 1.5
    },
    {
      "source": "n_85",
      "target": "n_89",
      "weight": 19.695071777664246,
      "distance": 14.06790841261732,
      "road_type": "service",
      "weight_factor": 1.4
    },
    {
      "source": "n_85",
      "target": "n_86",
      "weight": 64.83248309698362,
      "distance": 46.30891649784545,
      "road_type": "service",
      "weight_factor": 1.4
    },
    {
      "source": "n_86",
      "target": "n_88",
      "weight": 80.3450592651912,
      "distance": 57.38932804656515,
      "road_type": "service",
      "weight_factor": 1.4
    },
    {
      "source": "n_87",
      "target": "n_88",
      "weight": 106.51738675246824,
      "distance": 76.08384768033446,
      "road_type": "service",
      "weight_factor": 1.4
    },
    {
      "source": "n_87",
      "target": "b_11",
      "weight": 64.525879432729,
      "distance": 43.01725295515267,
      "road_type": "footway",
      "weight_factor": 1.5
    },
    {
      "source": "n_87",
      "target": "b_34",
      "weight": 53.00184625132297,
      "distance": 35.33456416754864,
      "road_type": "footway",
      "weight_factor": 1.5
    },
    {
      "source": "n_88",
      "target": "b_12",
      "weight": 35.71396660534989,
      "distance": 23.80931107023326,
      "road_type": "footway",
      "weight_factor": 1.5
    },
    {
      "source": "n_89",
      "target": "n_90",
      "weight": 35.505795584156076,
      "distance": 25.361282560111484,
      "road_type": "service",
      "weight_factor": 1.4
    },
    {
      "source": "n_89",
      "target": "n_94",
      "weight": 74.39520370377778,
      "distance": 53.139431216984136,
      "road_type": "service",
      "weight_factor": 1.4
    },
    {
      "source": "n_89",
      "target": "b_21",
      "weight": 29.359806676337445,
      "distance": 19.57320445089163,
      "road_type": "footway",
      "weight_factor": 1.5
    },
    {
      "source": "n_90",
      "target": "n_91",
      "weight": 53.03060370553275,
      "distance": 37.87900264680911,
      "road_type": "service",
      "weight_factor": 1.4
    },
    {
      "source": "n_91",
      "target": "n_92",
      "weight": 47.7675654373124,
      "distance": 34.11968959808029,
      "road_type": "service",
      "weight_factor": 1.4
    },
    {
      "source": "n_92",
      "target": "n_93",
      "weight": 15.039199048202676,
      "distance": 10.742285034430484,
      "road_type": "service",
      "weight_factor": 1.4
    },
    {
      "source": "n_92",
      "target": "n_165",
      "weight": 48.115597884777586,
      "distance": 34.368284203412564,
      "road_type": "service",
      "weight_factor": 1.4
    },
    {
      "source": "n_93",
      "target": "b_20",
      "weight": 28.257029257464872,
      "distance": 18.83801950497658,
      "road_type": "footway",
      "weight_factor": 1.5
    },
    {
      "source": "n_94",
      "target": "n_167",
      "weight": 13.5107077765983,
      "distance": 9.650505554713073,
      "road_type": "service",
      "weight_factor": 1.4
    },
    {
      "source": "n_94",
      "target": "n_168",
      "weight": 10.996919401078644,
      "distance": 7.8549424293418895,
      "road_type": "service",
      "weight_factor": 1.4
    },
    {
      "source": "n_95",
      "target": "n_118",
      "weight": 101.90989269215348,
      "distance": 72.79278049439534,
      "road_type": "service",
      "weight_factor": 1.4
    },
    {
      "source": "n_95",
      "target": "n_122",
      "weight": 77.4383544921875,
      "distance": 55.3131103515625,
      "road_type": "service",
      "weight_factor": 1.4
    },
    {
      "source": "n_96",
      "target": "n_97",
      "weight": 113.21643607113536,
      "distance": 80.86888290795383,
      "road_type": "service",
      "weight_factor": 1.4
    },
    {
      "source": "n_97",
      "target": "n_121",
      "weight": 111.54647065691982,
      "distance": 79.67605046922844,
      "road_type": "service",
      "weight_factor": 1.4
    },
    {
      "source": "n_98",
      "target": "n_105",
      "weight": 114.06850619375479,
      "distance": 81.47750442411058,
      "road_type": "service",
      "weight_factor": 1.4
    },
    {
      "source": "n_99",
      "target": "n_100",
      "weight": 113.29072879728317,
      "distance": 80.92194914091655,
      "road_type": "service",
      "weight_factor": 1.4
    },
    {
      "source": "n_100",
      "target": "n_101",
      "weight": 25.032437596681444,
      "distance": 17.880312569058173,
      "road_type": "service",
      "weight_factor": 1.4
    },
    {
      "source": "n_101",
      "target": "n_102",
      "weight": 9.745636988545424,
      "distance": 6.961169277532448,
      "road_type": "service",
      "weight_factor": 1.4
    },
    {
      "source": "n_102",
      "target": "n_103",
      "weight": 19.22607421875,
      "distance": 13.73291015625,
      "road_type": "service",
      "weight_factor": 1.4
    },
    {
      "source": "n_103",
      "target": "n_104",
      "weight": 72.43719386712046,
      "distance": 51.7408527622289,
      "road_type": "service",
      "weight_factor": 1.4
    },
    {
      "source": "n_104",
      "target": "n_106",
      "weight": 352.5508458606603,
      "distance": 251.8220327576145,
      "road_type": "service",
      "weight_factor": 1.4
    },
    {
      "source": "n_105",
      "target": "n_117",
      "weight": 21.68694817042979,
      "distance": 15.490677264592707,
      "road_type": "service",
      "weight_factor": 1.4
    },
    {
      "source": "n_106",
      "target": "n_107",
      "weight": 18.189347009503905,
      "distance": 12.992390721074221,
      "road_type": "service",
      "weight_factor": 1.4
    },
    {
      "source": "n_107",
      "target": "n_108",
      "weight": 13.5107077765983,
      "distance": 9.650505554713073,
      "road_type": "service",
      "weight_factor": 1.4
    },
    {
      "source": "n_108",
      "target": "n_109",
      "weight": 58.36885725363915,
      "distance": 41.69204089545654,
      "road_type": "service",
      "weight_factor": 1.4
    },
    {
      "source": "n_109",
      "target": "n_110",
      "weight": 33.77676944149575,
      "distance": 24.126263886782677,
      "road_type": "service",
      "weight_factor": 1.4
    },
    {
      "source": "n_110",
      "target": "n_111",
      "weight": 20.773399714879922,
      "distance": 14.83814265348566,
      "road_type": "service",
      "weight_factor": 1.4
    },
    {
      "source": "n_111",
      "target": "n_112",
      "weight": 23.44993420420853,
      "distance": 16.749953003006095,
      "road_type": "service",
      "weight_factor": 1.4
    },
    {
      "source": "n_112",
      "target": "n_113",
      "weight": 24.618839722080313,
      "distance": 17.584885515771653,
      "road_type": "service",
      "weight_factor": 1.4
    },
    {
      "source": "n_113",
      "target": "n_114",
      "weight": 19.255721228216494,
      "distance": 13.75408659158321,
      "road_type": "service",
      "weight_factor": 1.4
    },
    {
      "source": "n_114",
      "target": "n_115",
      "weight": 15.779572588937238,
      "distance": 11.271123277812316,
      "road_type": "service",
      "weight_factor": 1.4
    },
    {
      "source": "n_115",
      "target": "n_116",
      "weight": 17.752897792078038,
      "distance": 12.680641280055742,
      "road_type": "service",
      "weight_factor": 1.4
    },
    {
      "source": "n_116",
      "target": "n_117",
      "weight": 13.038008012410875,
      "distance": 9.312862866007768,
      "road_type": "service",
      "weight_factor": 1.4
    },
    {
      "source": "n_118",
      "target": "n_119",
      "weight": 146.14455224617868,
      "distance": 104.38896589012765,
      "road_type": "service",
      "weight_factor": 1.4
    },
    {
      "source": "n_119",
      "target": "n_120",
      "weight": 22.531915552994217,
      "distance": 16.09422539499587,
      "road_type": "service",
      "weight_factor": 1.4
    },
    {
      "source": "n_122",
      "target": "n_123",
      "weight": 22.30929413138396,
      "distance": 15.935210093845688,
      "road_type": "service",
      "weight_factor": 1.4
    },
    {
      "source": "n_122",
      "target": "n_128",
      "weight": 20.46911243853113,
      "distance": 14.620794598950805,
      "road_type": "service",
      "weight_factor": 1.4
    },
    {
      "source": "n_123",
      "target": "n_124",
      "weight": 147.26535903972416,
      "distance": 105.18954217123155,
      "road_type": "service",
      "weight_factor": 1.4
    },
    {
      "source": "n_123",
      "target": "b_3",
      "weight": 51.06137649623161,
      "distance": 34.04091766415441,
      "road_type": "footway",
      "weight_factor": 1.5
    },
    {
      "source": "n_124",
      "target": "n_125",
      "weight": 6.9427490234375,
      "distance": 4.9591064453125,
      "road_type": "service",
      "weight_factor": 1.4
    },
    {
      "source": "n_125",
      "target": "n_126",
      "weight": 5.340576171875,
      "distance": 3.814697265625,
      "road_type": "service",
      "weight_factor": 1.4
    },
    {
      "source": "n_126",
      "target": "n_127",
      "weight": 5.446340422843855,
      "distance": 3.8902431591741826,
      "road_type": "service",
      "weight_factor": 1.4
    },
    {
      "source": "n_128",
      "target": "n_129",
      "weight": 11.858003477342347,
      "distance": 8.470002483815962,
      "road_type": "service",
      "weight_factor": 1.4
    },
    {
      "source": "n_129",
      "target": "n_130",
      "weight": 8.13452327591665,
      "distance": 5.810373768511893,
      "road_type": "service",
      "weight_factor": 1.4
    },
    {
      "source": "n_131",
      "target": "n_132",
      "weight": 171.10275929063218,
      "distance": 122.21625663616585,
      "road_type": "service",
      "weight_factor": 1.4
    },
    {
      "source": "n_131",
      "target": "b_14",
      "weight": 66.00338835138953,
      "distance": 44.00225890092636,
      "road_type": "footway",
      "weight_factor": 1.5
    },
    {
      "source": "n_131",
      "target": "b_32",
      "weight": 57.174121540967136,
      "distance": 38.116081027311424,
      "road_type": "footway",
      "weight_factor": 1.5
    },
    {
      "source": "n_131",
      "target": "b_35",
      "weight": 71.70204085422048,
      "distance": 47.80136056948032,
      "road_type": "footway",
      "weight_factor": 1.5
    },
    {
      "source": "n_131",
      "target": "b_36",
      "weight": 66.53840350548033,
      "distance": 44.35893567032022,
      "road_type": "footway",
      "weight_factor": 1.5
    },
    {
      "source": "n_132",
      "target": "b_15",
      "weight": 84.55085235917875,
      "distance": 56.367234906119165,
      "road_type": "footway",
      "weight_factor": 1.5
    },
    {
      "source": "n_132",
      "target": "b_16",
      "weight": 40.14861038525382,
      "distance": 26.765740256835876,
      "road_type": "footway",
      "weight_factor": 1.5
    },
    {
      "source": "n_132",
      "target": "b_33",
      "weight": 24.66397760151991,
      "distance": 16.442651734346608,
      "road_type": "footway",
      "weight_factor": 1.5
    },
    {
      "source": "n_133",
      "target": "n_134",
      "weight": 322.38152616145544,
      "distance": 230.27251868675387,
      "road_type": "service",
      "weight_factor": 1.4
    },
    {
      "source": "n_133",
      "target": "b_18",
      "weight": 160.85760962025833,
      "distance": 107.23840641350556,
      "road_type": "footway",
      "weight_factor": 1.5
    },
    {
      "source": "n_135",
      "target": "n_136",
      "weight": 25.304414118461587,
      "distance": 18.07458151318685,
      "road_type": "service",
      "weight_factor": 1.4
    },
    {
      "source": "n_135",
      "target": "n_139",
      "weight": 77.71777024790435,
      "distance": 55.51269303421739,
      "road_type": "service",
      "weight_factor": 1.4
    },
    {
      "source": "n_135",
      "target": "n_140",
      "weight": 57.25137511157335,
      "distance": 40.893839365409534,
      "road_type": "service",
      "weight_factor": 1.4
    },
    {
      "source": "n_136",
      "target": "n_137",
      "weight": 17.656238828081634,
      "distance": 12.611599162915452,
      "road_type": "service",
      "weight_factor": 1.4
    },
    {
      "source": "n_137",
      "target": "n_138",
      "weight": 15.770532443486601,
      "distance": 11.264666031061859,
      "road_type": "service",
      "weight_factor": 1.4
    },
    {
      "source": "n_138",
      "target": "n_154",
      "weight": 14.37994142530118,
      "distance": 10.271386732357985,
      "road_type": "service",
      "weight_factor": 1.4
    },
    {
      "source": "n_138",
      "target": "n_155",
      "weight": 10.076578967955967,
      "distance": 7.197556405682834,
      "road_type": "service",
      "weight_factor": 1.4
    },
    {
      "source": "n_139",
      "target": "n_157",
      "weight": 25.003936576854663,
      "distance": 17.859954697753334,
      "road_type": "service",
      "weight_factor": 1.4
    },
    {
      "source": "n_141",
      "target": "n_142",
      "weight": 93.53787046052246,
      "distance": 66.81276461465889,
      "road_type": "service",
      "weight_factor": 1.4
    },
    {
      "source": "n_141",
      "target": "n_149",
      "weight": 7.024431233654886,
      "distance": 5.017450881182062,
      "road_type": "service",
      "weight_factor": 1.4
    },
    {
      "source": "n_141",
      "target": "n_144",
      "weight": 43.057101622077816,
      "distance": 30.75507258719845,
      "road_type": "service",
      "weight_factor": 1.4
    },
    {
      "source": "n_143",
      "target": "n_144",
      "weight": 90.48770686987669,
      "distance": 64.63407633562622,
      "road_type": "service",
      "weight_factor": 1.4
    },
    {
      "source": "n_144",
      "target": "n_145",
      "weight": 82.63409156427925,
      "distance": 59.02435111734231,
      "road_type": "service",
      "weight_factor": 1.4
    },
    {
      "source": "n_144",
      "target": "n_150",
      "weight": 34.445681297662254,
      "distance": 24.604058069758757,
      "road_type": "service",
      "weight_factor": 1.4
    },
    {
      "source": "n_146",
      "target": "n_147",
      "weight": 89.06441590272874,
      "distance": 63.617439930520526,
      "road_type": "service",
      "weight_factor": 1.4
    },
    {
      "source": "n_147",
      "target": "n_148",
      "weight": 84.92691630443699,
      "distance": 60.662083074597845,
      "road_type": "service",
      "weight_factor": 1.4
    },
    {
      "source": "n_147",
      "target": "n_150",
      "weight": 6.250984144213666,
      "distance": 4.464988674438334,
      "road_type": "service",
      "weight_factor": 1.4
    },
    {
      "source": "n_147",
      "target": "n_151",
      "weight": 32.38433091753196,
      "distance": 23.131664941094257,
      "road_type": "service",
      "weight_factor": 1.4
    },
    {
      "source": "n_149",
      "target": "n_152",
      "weight": 73.0566615545852,
      "distance": 52.18332968184657,
      "road_type": "service",
      "weight_factor": 1.4
    },
    {
      "source": "n_152",
      "target": "n_153",
      "weight": 20.545606755325228,
      "distance": 14.675433396660875,
      "road_type": "service",
      "weight_factor": 1.4
    },
    {
      "source": "n_153",
      "target": "n_154",
      "weight": 16.718647903059342,
      "distance": 11.9418913593281,
      "road_type": "service",
      "weight_factor": 1.4
    },
    {
      "source": "n_155",
      "target": "n_156",
      "weight": 24.215847272119888,
      "distance": 17.297033765799917,
      "road_type": "service",
      "weight_factor": 1.4
    },
    {
      "source": "n_156",
      "target": "n_157",
      "weight": 27.46635012645463,
      "distance": 19.618821518896166,
      "road_type": "service",
      "weight_factor": 1.4
    },
    {
      "source": "n_158",
      "target": "n_165",
      "weight": 70.94930821764757,
      "distance": 50.67807729831969,
      "road_type": "service",
      "weight_factor": 1.4
    },
    {
      "source": "n_158",
      "target": "n_169",
      "weight": 83.40878969572904,
      "distance": 59.57770692552075,
      "road_type": "service",
      "weight_factor": 1.4
    },
    {
      "source": "n_159",
      "target": "n_160",
      "weight": 13.688970844396067,
      "distance": 9.777836317425763,
      "road_type": "service",
      "weight_factor": 1.4
    },
    {
      "source": "n_160",
      "target": "n_161",
      "weight": 12.604212348700198,
      "distance": 9.003008820500142,
      "road_type": "service",
      "weight_factor": 1.4
    },
    {
      "source": "n_161",
      "target": "n_162",
      "weight": 136.88554126612007,
      "distance": 97.7753866186572,
      "road_type": "service",
      "weight_factor": 1.4
    },
    {
      "source": "n_162",
      "target": "n_163",
      "weight": 26.515301852766374,
      "distance": 18.939501323404556,
      "road_type": "service",
      "weight_factor": 1.4
    },
    {
      "source": "n_163",
      "target": "n_164",
      "weight": 18.157958984374996,
      "distance": 12.969970703125,
      "road_type": "service",
      "weight_factor": 1.4
    },
    {
      "source": "n_164",
      "target": "n_165",
      "weight": 24.618839722080313,
      "distance": 17.584885515771653,
      "road_type": "service",
      "weight_factor": 1.4
    },
    {
      "source": "n_166",
      "target": "n_167",
      "weight": 11.749267578125,
      "distance": 8.392333984375,
      "road_type": "service",
      "weight_factor": 1.4
    },
    {
      "source": "n_166",
      "target": "b_22",
      "weight": 50.81075529597889,
      "distance": 33.87383686398593,
      "road_type": "footway",
      "weight_factor": 1.5
    },
    {
      "source": "n_168",
      "target": "n_169",
      "weight": 10.203156450027432,
      "distance": 7.287968892876739,
      "road_type": "service",
      "weight_factor": 1.4
    },
    {
      "source": "n_168",
      "target": "b_23",
      "weight": 45.79823074045453,
      "distance": 30.532153826969683,
      "road_type": "footway",
      "weight_factor": 1.5
    },
    {
      "source": "n_173",
      "target": "n_174",
      "weight": 25.834260973246693,
      "distance": 18.453043552319066,
      "road_type": "service",
      "weight_factor": 1.4
    },
    {
      "source": "n_174",
      "target": "n_175",
      "weight": 44.61858826276792,
      "distance": 31.870420187691376,
      "road_type": "service",
      "weight_factor": 1.4
    },
    {
      "source": "n_175",
      "target": "n_185",
      "weight": 183.16307751083008,
      "distance": 130.83076965059294,
      "road_type": "service",
      "weight_factor": 1.4
    },
    {
      "source": "n_176",
      "target": "n_177",
      "weight": 7.263968930141305,
      "distance": 5.188549235815217,
      "road_type": "service",
      "weight_factor": 1.4
    },
    {
      "source": "n_178",
      "target": "n_179",
      "weight": 66.9278823941519,
      "distance": 47.80563028153707,
      "road_type": "service",
      "weight_factor": 1.4
    },
    {
      "source": "n_178",
      "target": "n_180",
      "weight": 72.13732729658372,
      "distance": 51.526662354702665,
      "road_type": "service",
      "weight_factor": 1.4
    },
    {
      "source": "n_178",
      "target": "n_181",
      "weight": 60.76064366045852,
      "distance": 43.40045975747038,
      "road_type": "service",
      "weight_factor": 1.4
    },
    {
      "source": "n_179",
      "target": "n_182",
      "weight": 74.32424426257545,
      "distance": 53.08874590183961,
      "road_type": "service",
      "weight_factor": 1.4
    },
    {
      "source": "n_179",
      "target": "b_28",
      "weight": 102.64677705862147,
      "distance": 68.43118470574765,
      "road_type": "footway",
      "weight_factor": 1.5
    },
    {
      "source": "n_180",
      "target": "n_182",
      "weight": 67.07899736129947,
      "distance": 47.91356954378535,
      "road_type": "service",
      "weight_factor": 1.4
    },
    {
      "source": "n_180",
      "target": "n_183",
      "weight": 31.108569688255272,
      "distance": 22.22040692018234,
      "road_type": "service",
      "weight_factor": 1.4
    },
    {
      "source": "n_180",
      "target": "b_27",
      "weight": 56.90714774235417,
      "distance": 37.93809849490278,
      "road_type": "footway",
      "weight_factor": 1.5
    },
    {
      "source": "n_182",
      "target": "n_186",
      "weight": 76.44303060643324,
      "distance": 54.602164718880886,
      "road_type": "service",
      "weight_factor": 1.4
    },
    {
      "source": "n_183",
      "target": "n_184",
      "weight": 19.695071777664246,
      "distance": 14.06790841261732,
      "road_type": "service",
      "weight_factor": 1.4
    },
    {
      "source": "n_184",
      "target": "b_26",
      "weight": 48.00546682845013,
      "distance": 32.003644552300095,
      "road_type": "footway",
      "weight_factor": 1.5
    },
    {
      "source": "n_185",
      "target": "n_186",
      "weight": 219.11206679821737,
      "distance": 156.50861914158386,
      "road_type": "service",
      "weight_factor": 1.4
    },
    {
      "source": "n_185",
      "target": "b_29",
      "weight": 101.55788168871085,
      "distance": 67.70525445914058,
      "road_type": "footway",
      "weight_factor": 1.5
    },
    {
      "source": "n_186",
      "target": "n_187",
      "weight": 28.0214896717573,
      "distance": 20.015349765540932,
      "road_type": "service",
      "weight_factor": 1.4
    },
    {
      "source": "n_187",
      "target": "n_188",
      "weight": 113.76806184531947,
      "distance": 81.26290131808534,
      "road_type": "service",
      "weight_factor": 1.4
    },
    {
      "source": "n_188",
      "target": "n_189",
      "weight": 21.528550811038908,
      "distance": 15.377536293599224,
      "road_type": "service",
      "weight_factor": 1.4
    },
    {
      "source": "n_189",
      "target": "n_190",
      "weight": 53.41644180319208,
      "distance": 38.154601287994346,
      "road_type": "service",
      "weight_factor": 1.4
    },
    {
      "source": "n_190",
      "target": "n_191",
      "weight": 14.576936103468821,
      "distance": 10.412097216763442,
      "road_type": "service",
      "weight_factor": 1.4
    },
    {
      "source": "n_191",
      "target": "n_192",
      "weight": 13.854652770616138,
      "distance": 9.8961805504401,
      "road_type": "service",
      "weight_factor": 1.4
    },
    {
      "source": "n_193",
      "target": "n_194",
      "weight": 150.9267991788899,
      "distance": 107.80485655634993,
      "road_type": "service",
      "weight_factor": 1.4
    },
    {
      "source": "n_193",
      "target": "n_196",
      "weight": 102.14890321293532,
      "distance": 72.9635022949538,
      "road_type": "service",
      "weight_factor": 1.4
    },
    {
      "source": "n_193",
      "target": "b_6",
      "weight": 84.87704428314686,
      "distance": 56.58469618876457,
      "road_type": "footway",
      "weight_factor": 1.5
    },
    {
      "source": "n_194",
      "target": "n_198",
      "weight": 54.8495633149868,
      "distance": 39.178259510704855,
      "road_type": "service",
      "weight_factor": 1.4
    },
    {
      "source": "n_194",
      "target": "n_199",
      "weight": 35.505795584156076,
      "distance": 25.361282560111484,
      "road_type": "service",
      "weight_factor": 1.4
    },
    {
      "source": "n_195",
      "target": "n_196",
      "weight": 150.19462558008865,
      "distance": 107.28187541434905,
      "road_type": "service",
      "weight_factor": 1.4
    },
    {
      "source": "n_195",
      "target": "n_197",
      "weight": 18.283187771662266,
      "distance": 13.05941983690162,
      "road_type": "service",
      "weight_factor": 1.4
    },
    {
      "source": "n_195",
      "target": "n_198",
      "weight": 46.303134199792765,
      "distance": 33.073667285566266,
      "road_type": "service",
      "weight_factor": 1.4
    },
    {
      "source": "n_196",
      "target": "b_9",
      "weight": 89.77384838325504,
      "distance": 59.84923225550335,
      "road_type": "footway",
      "weight_factor": 1.5
    },
    {
      "source": "n_198",
      "target": "b_8",
      "weight": 42.632874955799366,
      "distance": 28.421916637199573,
      "road_type": "footway",
      "weight_factor": 1.5
    },
    {
      "source": "n_199",
      "target": "b_7",
      "weight": 56.00889287249721,
      "distance": 37.33926191499815,
      "road_type": "footway",
      "weight_factor": 1.5
    },
    {
      "source": "n_200",
      "target": "n_201",
      "weight": 53.85514969584938,
      "distance": 38.46796406846384,
      "road_type": "service",
      "weight_factor": 1.4
    }
  ],
  "road_type_weights": {
    "footway": 1.5,
    "path": 1.2,
    "pedestrian": 2.0,
    "steps": 2.5,
    "cycleway": 1.0,
    "living_street": 1.3,
    "service": 1.4,
    "track": 1.1,
    "residential": 1.7,
    "unclassified": 1.6,
    "tertiary": 1.8,
    "tertiary_link": 1.7,
    "secondary": 2.2,
    "secondary_link": 2.0,
    "primary": 2.5,
    "primary_link": 2.3,
    "trunk": 3.0,
    "trunk_link": 2.8,
    "default": 1.8
  }
}