{
  "上海工程技术大学现代交通工程中心-辅楼": {
    "name": "糖油粑粑",
    "cuisine": "特色小吃",
    "rating": 4.7,
    "popularity": 2
  },
  "上海工程技术大学图书馆": {
    "name": "蛋挞",
    "cuisine": "粤菜",
    "rating": 4.2,
    "popularity": 13
  },
  "上海工程技术大学第二食堂": {
    "name": "三明治",
    "cuisine": "快餐",
    "rating": 3.8,
    "popularity": 18
  },
  "上海工程技术大学教学楼J302教室": {
    "name": "葡萄酒",
    "cuisine": "饮品",
    "rating": 4.1,
    "popularity": 1
  },
  "上海工程技术大学研究生宿舍2号楼": {
    "name": "白酒",
    "cuisine": "饮品",
    "rating": 4.3,
    "popularity": 2
  },
  "上海工程技术大学实训楼": {
    "name": "佛跳墙",
    "cuisine": "闽菜",
    "rating": 3.9,
    "popularity": 15
  },
  "上海工程技术大学实训楼5号楼": {
    "name": "布丁",
    "cuisine": "甜品",
    "rating": 4.0,
    "popularity": 9
  },
  "上海工程技术大学艺术楼": {
    "name": "烤羊肉串",
    "cuisine": "美食街特色",
    "rating": 4.2,
    "popularity": 8
  },
  "上海工程技术大学风雨操场": {
    "name": "刺身拼盘",
    "cuisine": "日式",
    "rating": 5,
    "popularity": 9
  },
  "上海工程技术大学第二图文信息中心": {
    "name": "煲仔饭",
    "cuisine": "粤菜",
    "rating": 3.4,
    "popularity": 10
  },
  "上海工程技术大学教学楼C楼": {
    "name": "烧鹅",
    "cuisine": "粤菜",
    "rating": 4.6,
    "popularity": 13
  },
  "上海工程技术大学教学楼J303教室": {
    "name": "莆田卤面",
    "cuisine": "闽菜",
    "rating": 3.2,
    "popularity": 7
  },
  "志宏堂报告厅": {
    "name": "阿拉伯烤全羊",
    "cuisine": "中东菜",
    "rating": 5,
    "popularity": 1
  },
  "上海工程技术大学保卫处": {
    "name": "汉堡",
    "cuisine": "快餐",
    "rating": 4.2,
    "popularity": 11
  },
  "上海工程技术大学教学楼B楼": {
    "name": "蒜蓉蒸龙虾",
    "cuisine": "海鲜",
    "rating": 4.5,
    "popularity": 1
  },
  "上海工程技术大学第一食堂": {
    "name": "豆浆",
    "cuisine": "特色小吃",
    "rating": 3.5,
    "popularity": 3
  },
  "上海工程技术大学研究生宿舍1号楼": {
    "name": "灌肠",
    "cuisine": "京菜",
    "rating": 4.5,
    "popularity": 17
  },
  "上海工程技术大学教学楼F楼": {
    "name": "炒粉",
    "cuisine": "其他",
    "rating": 3.8,
    "popularity": 6
  },
  "上海工程技术大学现代交通工程中心": {
    "name": "蛋糕",
    "cuisine": "甜品",
    "rating": 3.1,
    "popularity": 1
  },
  "上海工程技术大学教学楼A楼": {
    "name": "意大利披萨",
    "cuisine": "西式",
    "rating": 4.0,
    "popularity": 7
  }
}